{
  "metadata": {
    "comment": "",
    "campaign": "VALIDATION_DATA",
    "damage_events": "NO_EVENT",
    "driver_id": "2169",
    "driving_side": "RIGHT_DRIVING_SIDE",
    "steering_wheel_side": "LEFT_HAND_DRIVE",
    "camera_serial_number": "DCC0602",
    "vehicle_id": "WAUZZZF22KN080690",
    "extrinsic": {
      "__comment": "Global referencepoint is related to middle of rear axle",
      "antennas": {
        "antenna_left": {
          "origin": "[0.68763.,0.47402,1.06414]",
          "yaw": "0",
          "roll": "0",
          "pitch": "0"
        },
        "antenna_right": {
          "origin": "[0.68771,-0.46729,1.06531]",
          "yaw": "0",
          "roll": "0",
          "pitch": "0"
        }
      },
      "cameras": {
        "camera_front_1": {
          "origin": "[1.84627,0.0044,0.9467]",
          "yaw": "0",
          "roll": "0",
          "pitch": "0"
        }
      },
      "imu": {
        "origin": "[0.24625,0.0025,0.08]",
        "yaw": "0",
        "roll": "0",
        "pitch": "0"
      },
      "lidars": {
        "lidar_left": {
          "origin": "[1.63826,0.52197,1.11220]",
          "yaw": "0",
          "roll": "15",
          "pitch": "0"
        },
        "lidar_front": {
          "origin": "[1.6815,-0.00313,1.11218]",
          "yaw": "0",
          "roll": "0",
          "pitch": "0"
        },
        "lidar_right": {
          "origin": "[1.63833,-0.52254,1.1105]",
          "yaw": "0",
          "roll": "-15",
          "pitch": "0"
        }
      }
    },
    "governance": {
      "location": "Ingolstadt",
      "pool": "audi_mfk5_camera"
    },
    "rear_axle_steering": "YES",
    "logger_sw_version": "5.01.F070",
    "logger": "X2E",
    "ros_visualization_version": "5.2.0",
    "meta_data_version": "1.2.0",
    "vehicle_number_plate": "AB-ME 7200",
    "group_project_name": "MFK5",
    "vehicle_region": "EUROPE_EU",
    "brand": "AUDI",
    "tire_type": "SUMMER_TIRE",
    "windshield_number_front": "9",
    "vehicle_load_change": "BAGGAGE_REMOVED",
    "group_vehicle_number": "AU416000000",
    "workshop_events": "NO_EVENT",
    "windshield_type_front": "GREEN_GLASS_HUD",
    "country": "TW",
    "region": "ASIA_AND_ASIA_PACIFIC",
    "test_track_id": "MFK5",
    "windshield_serial_number_front": "4K8 845 099 B",
    "vehicle_platform": "PPE",
    "time": {
      "timestamp": 1663902242369602918,
      "domain": "UTC",
      "confidence_class": "AUTO_RETRIEVAL"
    },
    "suspension_system": "STEEL",
    "position": {
      "source": "GPS",
      "domain": "WGS84",
      "confidence_class": "AUTO_RETRIEVAL"
    },
    "model": "A7",
    "us_state": "",
    "headlight_type": "LED",
    "CarryoverFromMFK5": true
  },
  "prelabels": [
    {
      "category": "WeatherCloudiness",
      "postion_coordinates": {
        "latitude": 25.09574074040682,
        "elevation": 75.48387145996094,
        "longitude": 121.73893101359637
      },
      "timestamp": 1663902274419522047,
      "clipnumber": -1,
      "label": "CL_PARTIALLY_CLOUDY",
      "clipname_video": "N/A",
      "state": "activated",
      "conditions": {
        "WeatherCloudiness": [
          "CL_PARTIALLY_CLOUDY"
        ]
      },
      "type": "multi-select",
      "frame_number": 3576
    },
    {
      "category": "WeatherPrecipitation",
      "postion_coordinates": {
        "latitude": 25.095780536550688,
        "elevation": 75.62735748291016,
        "longitude": 121.73892719581967
      },
      "timestamp": 1663902274799962043,
      "clipnumber": -1,
      "label": "PR_NO",
      "clipname_video": "N/A",
      "state": "activated",
      "conditions": {
        "WeatherPrecipitation": [
          "PR_NO"
        ],
        "WeatherCloudiness": [
          "CL_PARTIALLY_CLOUDY"
        ]
      },
      "type": "multi-select",
      "frame_number": 3576
    },
    {
      "category": "WeatherLight",
      "postion_coordinates": {
        "latitude": 25.09585095194313,
        "elevation": 75.86172485351562,
        "longitude": 121.73892022833687
      },
      "timestamp": 1663902275389647006,
      "clipnumber": -1,
      "label": "LI_DAY",
      "clipname_video": "N/A",
      "state": "activated",
      "conditions": {
        "WeatherPrecipitation": [
          "PR_NO"
        ],
        "WeatherCloudiness": [
          "CL_PARTIALLY_CLOUDY"
        ],
        "WeatherLight": [
          "LI_DAY"
        ]
      },
      "type": "multi-select",
      "frame_number": 3620
    },
    {
      "category": "ConditionsRoadCategory",
      "postion_coordinates": {
        "latitude": 25.096030740322032,
        "elevation": 76.44308471679688,
        "longitude": 121.73890099199832
      },
      "timestamp": 1663902277339482069,
      "clipnumber": -1,
      "label": "RC_COUNTRY_ROADS",
      "clipname_video": "N/A",
      "state": "activated",
      "conditions": {
        "WeatherPrecipitation": [
          "PR_NO"
        ],
        "WeatherCloudiness": [
          "CL_PARTIALLY_CLOUDY"
        ],
        "ConditionsRoadCategory": [
          "RC_COUNTRY_ROADS"
        ],
        "WeatherLight": [
          "LI_DAY"
        ]
      },
      "type": "multi-select",
      "frame_number": 3688
    },
    {
      "category": "ConditionsRoadType",
      "postion_coordinates": {
        "latitude": 25.096147779466207,
        "elevation": 76.76405334472656,
        "longitude": 121.73888754757277
      },
      "timestamp": 1663902278409473896,
      "clipnumber": -1,
      "label": "RT_PAVED",
      "clipname_video": "N/A",
      "state": "activated",
      "conditions": {
        "WeatherPrecipitation": [
          "PR_NO"
        ],
        "ConditionsRoadType": [
          "RT_PAVED"
        ],
        "WeatherCloudiness": [
          "CL_PARTIALLY_CLOUDY"
        ],
        "ConditionsRoadCategory": [
          "RC_COUNTRY_ROADS"
        ],
        "WeatherLight": [
          "LI_DAY"
        ]
      },
      "type": "multi-select",
      "frame_number": 3726
    },
    {
      "category": "ConditionsRoadState",
      "postion_coordinates": {
        "latitude": 25.09624223758296,
        "elevation": 77.02595520019531,
        "longitude": 121.73887726513681
      },
      "timestamp": 1663902279279534101,
      "clipnumber": -1,
      "label": "ROAD_DRY",
      "clipname_video": "N/A",
      "state": "activated",
      "conditions": {
        "WeatherPrecipitation": [
          "PR_NO"
        ],
        "ConditionsRoadCategory": [
          "RC_COUNTRY_ROADS"
        ],
        "WeatherCloudiness": [
          "CL_PARTIALLY_CLOUDY"
        ],
        "ConditionsRoadState": [
          "ROAD_DRY"
        ],
        "ConditionsRoadType": [
          "RT_PAVED"
        ],
        "WeatherLight": [
          "LI_DAY"
        ]
      },
      "type": "multi-select",
      "frame_number": 3764
    },
    {
      "category": "ConditionsLaneColor",
      "postion_coordinates": {
        "latitude": 25.097122474184896,
        "elevation": 80.52261352539062,
        "longitude": 121.7387784121443
      },
      "timestamp": 1663902289169483900,
      "clipnumber": -1,
      "label": "LC_RED_GREEN_ORANGE",
      "clipname_video": "N/A",
      "state": "activated",
      "conditions": {
        "WeatherPrecipitation": [
          "PR_NO"
        ],
        "ConditionsLaneColor": [
          "LC_RED_GREEN_ORANGE"
        ],
        "ConditionsRoadCategory": [
          "RC_COUNTRY_ROADS"
        ],
        "WeatherCloudiness": [
          "CL_PARTIALLY_CLOUDY"
        ],
        "ConditionsRoadState": [
          "ROAD_DRY"
        ],
        "ConditionsRoadType": [
          "RT_PAVED"
        ],
        "WeatherLight": [
          "LI_DAY"
        ]
      },
      "type": "multi-select",
      "frame_number": 4118
    },
    {
      "category": "Signs",
      "postion_coordinates": {
        "latitude": 25.098385146091328,
        "elevation": 77.18192291259766,
        "longitude": 121.73833907851132
      },
      "timestamp": 1663902307941138982,
      "clipnumber": -1,
      "label": "SIGN_PAVEMENT",
      "clipname_video": "N/A",
      "state": "",
      "conditions": {
        "WeatherPrecipitation": [
          "PR_NO"
        ],
        "ConditionsLaneColor": [
          "LC_RED_GREEN_ORANGE"
        ],
        "ConditionsRoadCategory": [
          "RC_COUNTRY_ROADS"
        ],
        "WeatherCloudiness": [
          "CL_PARTIALLY_CLOUDY"
        ],
        "ConditionsRoadState": [
          "ROAD_DRY"
        ],
        "ConditionsRoadType": [
          "RT_PAVED"
        ],
        "WeatherLight": [
          "LI_DAY"
        ]
      },
      "type": "single",
      "frame_number": 4770
    },
    {
      "category": "Signs",
      "postion_coordinates": {
        "latitude": 25.09862196839942,
        "elevation": 74.302001953125,
        "longitude": 121.73798261205052
      },
      "timestamp": 1663902312259524106,
      "clipnumber": -1,
      "label": "SIGN_PAVEMENT",
      "clipname_video": "N/A",
      "state": "",
      "conditions": {
        "WeatherPrecipitation": [
          "PR_NO"
        ],
        "ConditionsLaneColor": [
          "LC_RED_GREEN_ORANGE"
        ],
        "ConditionsRoadCategory": [
          "RC_COUNTRY_ROADS"
        ],
        "WeatherCloudiness": [
          "CL_PARTIALLY_CLOUDY"
        ],
        "ConditionsRoadState": [
          "ROAD_DRY"
        ],
        "ConditionsRoadType": [
          "RT_PAVED"
        ],
        "WeatherLight": [
          "LI_DAY"
        ]
      },
      "type": "single",
      "frame_number": 4954
    },
    {
      "category": "Signs",
      "postion_coordinates": {
        "latitude": 25.09940632005872,
        "elevation": 68.12583923339844,
        "longitude": 121.7369154909965
      },
      "timestamp": 1663902327579549074,
      "clipnumber": -1,
      "label": "SIGN_PAVEMENT",
      "clipname_video": "N/A",
      "state": "",
      "conditions": {
        "WeatherPrecipitation": [
          "PR_NO"
        ],
        "ConditionsLaneColor": [
          "LC_RED_GREEN_ORANGE"
        ],
        "ConditionsRoadCategory": [
          "RC_COUNTRY_ROADS"
        ],
        "WeatherCloudiness": [
          "CL_PARTIALLY_CLOUDY"
        ],
        "ConditionsRoadState": [
          "ROAD_DRY"
        ],
        "ConditionsRoadType": [
          "RT_PAVED"
        ],
        "WeatherLight": [
          "LI_DAY"
        ]
      },
      "type": "single",
      "frame_number": 5488
    },
    {
      "category": "Signs",
      "postion_coordinates": {
        "latitude": 25.099601426865735,
        "elevation": 66.96672821044922,
        "longitude": 121.73667686631508
      },
      "timestamp": 1663902332220211982,
      "clipnumber": -1,
      "label": "SIGN_WARNING",
      "clipname_video": "N/A",
      "state": "",
      "conditions": {
        "WeatherPrecipitation": [
          "PR_NO"
        ],
        "ConditionsLaneColor": [
          "LC_RED_GREEN_ORANGE"
        ],
        "ConditionsRoadCategory": [
          "RC_COUNTRY_ROADS"
        ],
        "WeatherCloudiness": [
          "CL_PARTIALLY_CLOUDY"
        ],
        "ConditionsRoadState": [
          "ROAD_DRY"
        ],
        "ConditionsRoadType": [
          "RT_PAVED"
        ],
        "WeatherLight": [
          "LI_DAY"
        ]
      },
      "type": "single",
      "frame_number": 5655
    },
    {
      "category": "Signs",
      "postion_coordinates": {
        "latitude": 25.099628311631005,
        "elevation": 66.78858184814453,
        "longitude": 121.73664196189702
      },
      "timestamp": 1663902332820171117,
      "clipnumber": -1,
      "label": "SIGN_SUPPLEMENTARY",
      "clipname_video": "N/A",
      "state": "",
      "conditions": {
        "WeatherPrecipitation": [
          "PR_NO"
        ],
        "ConditionsLaneColor": [
          "LC_RED_GREEN_ORANGE"
        ],
        "ConditionsRoadCategory": [
          "RC_COUNTRY_ROADS"
        ],
        "WeatherCloudiness": [
          "CL_PARTIALLY_CLOUDY"
        ],
        "ConditionsRoadState": [
          "ROAD_DRY"
        ],
        "ConditionsRoadType": [
          "RT_PAVED"
        ],
        "WeatherLight": [
          "LI_DAY"
        ]
      },
      "type": "single",
      "frame_number": 5655
    },
    {
      "category": "Signs",
      "postion_coordinates": {
        "latitude": 25.103465708091804,
        "elevation": 64.63800048828125,
        "longitude": 121.73558896768292
      },
      "timestamp": 1663902421589605093,
      "clipnumber": -1,
      "label": "SIGN_MANDATORY",
      "clipname_video": "N/A",
      "state": "",
      "conditions": {
        "WeatherPrecipitation": [
          "PR_NO"
        ],
        "ConditionsLaneColor": [
          "LC_RED_GREEN_ORANGE"
        ],
        "ConditionsRoadCategory": [
          "RC_COUNTRY_ROADS"
        ],
        "WeatherCloudiness": [
          "CL_PARTIALLY_CLOUDY"
        ],
        "ConditionsRoadState": [
          "ROAD_DRY"
        ],
        "ConditionsRoadType": [
          "RT_PAVED"
        ],
        "WeatherLight": [
          "LI_DAY"
        ]
      },
      "type": "single",
      "frame_number": 8868
    },
    {
      "category": "Signs",
      "postion_coordinates": {
        "latitude": 25.103588733259404,
        "elevation": 64.99378204345703,
        "longitude": 121.73551848277596
      },
      "timestamp": 1663902436309545993,
      "clipnumber": -1,
      "label": "SIGN_OTHER",
      "clipname_video": "N/A",
      "state": "",
      "conditions": {
        "WeatherPrecipitation": [
          "PR_NO"
        ],
        "ConditionsLaneColor": [
          "LC_RED_GREEN_ORANGE"
        ],
        "ConditionsRoadCategory": [
          "RC_COUNTRY_ROADS"
        ],
        "WeatherCloudiness": [
          "CL_PARTIALLY_CLOUDY"
        ],
        "ConditionsRoadState": [
          "ROAD_DRY"
        ],
        "ConditionsRoadType": [
          "RT_PAVED"
        ],
        "WeatherLight": [
          "LI_DAY"
        ]
      },
      "type": "single",
      "frame_number": 9402
    },
    {
      "category": "Signs",
      "postion_coordinates": {
        "latitude": 25.103603855102758,
        "elevation": 64.79090881347656,
        "longitude": 121.73534805371312
      },
      "timestamp": 1663902439379518032,
      "clipnumber": -1,
      "label": "SIGN_OTHER",
      "clipname_video": "N/A",
      "state": "",
      "conditions": {
        "WeatherPrecipitation": [
          "PR_NO"
        ],
        "ConditionsLaneColor": [
          "LC_RED_GREEN_ORANGE"
        ],
        "ConditionsRoadCategory": [
          "RC_COUNTRY_ROADS"
        ],
        "WeatherCloudiness": [
          "CL_PARTIALLY_CLOUDY"
        ],
        "ConditionsRoadState": [
          "ROAD_DRY"
        ],
        "ConditionsRoadType": [
          "RT_PAVED"
        ],
        "WeatherLight": [
          "LI_DAY"
        ]
      },
      "type": "single",
      "frame_number": 9516
    },
    {
      "category": "ConditionsRoadStructure",
      "postion_coordinates": {
        "latitude": 25.103559991198498,
        "elevation": 64.5590591430664,
        "longitude": 121.73523273107351
      },
      "timestamp": 1663902440999495029,
      "clipnumber": -1,
      "label": "RS_TUNNEL",
      "clipname_video": "N/A",
      "state": "activated",
      "conditions": {
        "WeatherPrecipitation": [
          "PR_NO"
        ],
        "ConditionsLaneColor": [
          "LC_RED_GREEN_ORANGE"
        ],
        "ConditionsRoadCategory": [
          "RC_COUNTRY_ROADS"
        ],
        "ConditionsRoadStructure": [
          "RS_TUNNEL"
        ],
        "WeatherCloudiness": [
          "CL_PARTIALLY_CLOUDY"
        ],
        "ConditionsRoadState": [
          "ROAD_DRY"
        ],
        "ConditionsRoadType": [
          "RT_PAVED"
        ],
        "WeatherLight": [
          "LI_DAY"
        ]
      },
      "type": "multi-select",
      "frame_number": 9550
    },
    {
      "category": "WeatherLight",
      "postion_coordinates": {
        "latitude": 25.10347887778563,
        "elevation": 64.04557037353516,
        "longitude": 121.73504111461159
      },
      "timestamp": 1663902443429503917,
      "clipnumber": -1,
      "label": "LI_DAY",
      "clipname_video": "N/A",
      "state": "deactivated",
      "conditions": {
        "WeatherPrecipitation": [
          "PR_NO"
        ],
        "ConditionsLaneColor": [
          "LC_RED_GREEN_ORANGE"
        ],
        "ConditionsRoadCategory": [
          "RC_COUNTRY_ROADS"
        ],
        "ConditionsRoadStructure": [
          "RS_TUNNEL"
        ],
        "WeatherCloudiness": [
          "CL_PARTIALLY_CLOUDY"
        ],
        "ConditionsRoadState": [
          "ROAD_DRY"
        ],
        "ConditionsRoadType": [
          "RT_PAVED"
        ],
        "WeatherLight": []
      },
      "type": "multi-select",
      "frame_number": 9656
    },
    {
      "category": "WeatherLight",
      "postion_coordinates": {
        "latitude": 25.10347887778563,
        "elevation": 64.04557037353516,
        "longitude": 121.73504111461159
      },
      "timestamp": 1663902443429503917,
      "clipnumber": -1,
      "label": "LI_ARTIFICIAL",
      "clipname_video": "N/A",
      "state": "activated",
      "conditions": {
        "WeatherPrecipitation": [
          "PR_NO"
        ],
        "ConditionsLaneColor": [
          "LC_RED_GREEN_ORANGE"
        ],
        "ConditionsRoadCategory": [
          "RC_COUNTRY_ROADS"
        ],
        "ConditionsRoadStructure": [
          "RS_TUNNEL"
        ],
        "WeatherCloudiness": [
          "CL_PARTIALLY_CLOUDY"
        ],
        "ConditionsRoadState": [
          "ROAD_DRY"
        ],
        "ConditionsRoadType": [
          "RT_PAVED"
        ],
        "WeatherLight": [
          "LI_ARTIFICIAL"
        ]
      },
      "type": "multi-select",
      "frame_number": 9656
    },
    {
      "category": "ConditionsRoadStructure",
      "postion_coordinates": {
        "latitude": 25.1044089987867,
        "elevation": 72.6805191040039,
        "longitude": 121.73448124067959
      },
      "timestamp": 1663902462269536972,
      "clipnumber": -1,
      "label": "RS_TUNNEL",
      "clipname_video": "N/A",
      "state": "deactivated",
      "conditions": {
        "WeatherPrecipitation": [
          "PR_NO"
        ],
        "ConditionsLaneColor": [
          "LC_RED_GREEN_ORANGE"
        ],
        "ConditionsRoadCategory": [
          "RC_COUNTRY_ROADS"
        ],
        "ConditionsRoadStructure": [],
        "WeatherCloudiness": [
          "CL_PARTIALLY_CLOUDY"
        ],
        "ConditionsRoadState": [
          "ROAD_DRY"
        ],
        "ConditionsRoadType": [
          "RT_PAVED"
        ],
        "WeatherLight": [
          "LI_ARTIFICIAL"
        ]
      },
      "type": "multi-select",
      "frame_number": 10343
    },
    {
      "category": "WeatherLight",
      "postion_coordinates": {
        "latitude": 25.104480274680334,
        "elevation": 73.31752014160156,
        "longitude": 121.73457483795953
      },
      "timestamp": 1663902463509490966,
      "clipnumber": -1,
      "label": "LI_ARTIFICIAL",
      "clipname_video": "N/A",
      "state": "deactivated",
      "conditions": {
        "WeatherPrecipitation": [
          "PR_NO"
        ],
        "ConditionsLaneColor": [
          "LC_RED_GREEN_ORANGE"
        ],
        "ConditionsRoadCategory": [
          "RC_COUNTRY_ROADS"
        ],
        "ConditionsRoadStructure": [],
        "WeatherCloudiness": [
          "CL_PARTIALLY_CLOUDY"
        ],
        "ConditionsRoadState": [
          "ROAD_DRY"
        ],
        "ConditionsRoadType": [
          "RT_PAVED"
        ],
        "WeatherLight": []
      },
      "type": "multi-select",
      "frame_number": 10383
    },
    {
      "category": "WeatherLight",
      "postion_coordinates": {
        "latitude": 25.104480274680334,
        "elevation": 73.31752014160156,
        "longitude": 121.73457483795953
      },
      "timestamp": 1663902463509490966,
      "clipnumber": -1,
      "label": "LI_DAY",
      "clipname_video": "N/A",
      "state": "activated",
      "conditions": {
        "WeatherPrecipitation": [
          "PR_NO"
        ],
        "ConditionsLaneColor": [
          "LC_RED_GREEN_ORANGE"
        ],
        "ConditionsRoadCategory": [
          "RC_COUNTRY_ROADS"
        ],
        "ConditionsRoadStructure": [],
        "WeatherCloudiness": [
          "CL_PARTIALLY_CLOUDY"
        ],
        "ConditionsRoadState": [
          "ROAD_DRY"
        ],
        "ConditionsRoadType": [
          "RT_PAVED"
        ],
        "WeatherLight": [
          "LI_DAY"
        ]
      },
      "type": "multi-select",
      "frame_number": 10383
    },
    {
      "category": "ConditionsRoadCategory",
      "postion_coordinates": {
        "latitude": 25.10451227082565,
        "elevation": 75.54623413085938,
        "longitude": 121.73582159984203
      },
      "timestamp": 1663902474071281909,
      "clipnumber": -1,
      "label": "RC_COUNTRY_ROADS",
      "clipname_video": "N/A",
      "state": "deactivated",
      "conditions": {
        "WeatherPrecipitation": [
          "PR_NO"
        ],
        "ConditionsLaneColor": [
          "LC_RED_GREEN_ORANGE"
        ],
        "ConditionsRoadCategory": [],
        "ConditionsRoadStructure": [],
        "WeatherCloudiness": [
          "CL_PARTIALLY_CLOUDY"
        ],
        "ConditionsRoadState": [
          "ROAD_DRY"
        ],
        "ConditionsRoadType": [
          "RT_PAVED"
        ],
        "WeatherLight": [
          "LI_DAY"
        ]
      },
      "type": "multi-select",
      "frame_number": 10742
    },
    {
      "category": "ConditionsRoadCategory",
      "postion_coordinates": {
        "latitude": 25.10451227082565,
        "elevation": 75.54623413085938,
        "longitude": 121.73582159984203
      },
      "timestamp": 1663902474071281909,
      "clipnumber": -1,
      "label": "RC_URBAN",
      "clipname_video": "N/A",
      "state": "activated",
      "conditions": {
        "WeatherPrecipitation": [
          "PR_NO"
        ],
        "ConditionsLaneColor": [
          "LC_RED_GREEN_ORANGE"
        ],
        "ConditionsRoadCategory": [
          "RC_URBAN"
        ],
        "ConditionsRoadStructure": [],
        "WeatherCloudiness": [
          "CL_PARTIALLY_CLOUDY"
        ],
        "ConditionsRoadState": [
          "ROAD_DRY"
        ],
        "ConditionsRoadType": [
          "RT_PAVED"
        ],
        "WeatherLight": [
          "LI_DAY"
        ]
      },
      "type": "multi-select",
      "frame_number": 10742
    },
    {
      "category": "ConditionsRoadCategory",
      "postion_coordinates": {
        "latitude": 25.104495001682174,
        "elevation": 74.69168090820312,
        "longitude": 121.7359123694773
      },
      "timestamp": 1663902474820127010,
      "clipnumber": -1,
      "label": "RC_URBAN",
      "clipname_video": "N/A",
      "state": "deactivated",
      "conditions": {
        "WeatherPrecipitation": [
          "PR_NO"
        ],
        "ConditionsLaneColor": [
          "LC_RED_GREEN_ORANGE"
        ],
        "ConditionsRoadCategory": [],
        "ConditionsRoadStructure": [],
        "WeatherCloudiness": [
          "CL_PARTIALLY_CLOUDY"
        ],
        "ConditionsRoadState": [
          "ROAD_DRY"
        ],
        "ConditionsRoadType": [
          "RT_PAVED"
        ],
        "WeatherLight": [
          "LI_DAY"
        ]
      },
      "type": "multi-select",
      "frame_number": 10778
    },
    {
      "category": "ConditionsRoadCategory",
      "postion_coordinates": {
        "latitude": 25.104495001682174,
        "elevation": 74.69168090820312,
        "longitude": 121.7359123694773
      },
      "timestamp": 1663902474820127010,
      "clipnumber": -1,
      "label": "RC_HIGHWAY",
      "clipname_video": "N/A",
      "state": "activated",
      "conditions": {
        "WeatherPrecipitation": [
          "PR_NO"
        ],
        "ConditionsLaneColor": [
          "LC_RED_GREEN_ORANGE"
        ],
        "ConditionsRoadCategory": [
          "RC_HIGHWAY"
        ],
        "ConditionsRoadStructure": [],
        "WeatherCloudiness": [
          "CL_PARTIALLY_CLOUDY"
        ],
        "ConditionsRoadState": [
          "ROAD_DRY"
        ],
        "ConditionsRoadType": [
          "RT_PAVED"
        ],
        "WeatherLight": [
          "LI_DAY"
        ]
      },
      "type": "multi-select",
      "frame_number": 10778
    },
    {
      "category": "Signs",
      "postion_coordinates": {
        "latitude": 25.104029399593635,
        "elevation": 66.90694427490234,
        "longitude": 121.73778924080973
      },
      "timestamp": 1663902487764185905,
      "clipnumber": -1,
      "label": "SIGN_SPEED_LIMIT_EXPLICIT",
      "clipname_video": "N/A",
      "state": "",
      "conditions": {
        "WeatherPrecipitation": [
          "PR_NO"
        ],
        "ConditionsLaneColor": [
          "LC_RED_GREEN_ORANGE"
        ],
        "ConditionsRoadCategory": [
          "RC_HIGHWAY"
        ],
        "ConditionsRoadStructure": [],
        "WeatherCloudiness": [
          "CL_PARTIALLY_CLOUDY"
        ],
        "ConditionsRoadState": [
          "ROAD_DRY"
        ],
        "ConditionsRoadType": [
          "RT_PAVED"
        ],
        "WeatherLight": [
          "LI_DAY"
        ]
      },
      "type": "single",
      "frame_number": 11250
    },
    {
      "category": "ConditionsLaneColor",
      "postion_coordinates": {
        "latitude": 25.10323764620984,
        "elevation": 62.86799621582031,
        "longitude": 121.74110430927118
      },
      "timestamp": 1663902512269505023,
      "clipnumber": -1,
      "label": "LC_RED_GREEN_ORANGE",
      "clipname_video": "N/A",
      "state": "deactivated",
      "conditions": {
        "WeatherPrecipitation": [
          "PR_NO"
        ],
        "ConditionsLaneColor": [],
        "ConditionsRoadCategory": [
          "RC_HIGHWAY"
        ],
        "ConditionsRoadStructure": [],
        "WeatherCloudiness": [
          "CL_PARTIALLY_CLOUDY"
        ],
        "ConditionsRoadState": [
          "ROAD_DRY"
        ],
        "ConditionsRoadType": [
          "RT_PAVED"
        ],
        "WeatherLight": [
          "LI_DAY"
        ]
      },
      "type": "multi-select",
      "frame_number": 12148
    },
    {
      "category": "Signs",
      "postion_coordinates": {
        "latitude": 25.10068479668388,
        "elevation": 73.25748443603516,
        "longitude": 121.7502926193172
      },
      "timestamp": 1663902584209522008,
      "clipnumber": -1,
      "label": "SIGN_SPEED_LIMIT_EXPLICIT",
      "clipname_video": "N/A",
      "state": "",
      "conditions": {
        "WeatherPrecipitation": [
          "PR_NO"
        ],
        "ConditionsLaneColor": [],
        "ConditionsRoadCategory": [
          "RC_HIGHWAY"
        ],
        "ConditionsRoadStructure": [],
        "WeatherCloudiness": [
          "CL_PARTIALLY_CLOUDY"
        ],
        "ConditionsRoadState": [
          "ROAD_DRY"
        ],
        "ConditionsRoadType": [
          "RT_PAVED"
        ],
        "WeatherLight": [
          "LI_DAY"
        ]
      },
      "type": "single",
      "frame_number": 14746
    },
    {
      "category": "Signs",
      "postion_coordinates": {
        "latitude": 25.100687532816128,
        "elevation": 73.28238677978516,
        "longitude": 121.75031947332653
      },
      "timestamp": 1663902584419579982,
      "clipnumber": -1,
      "label": "SIGN_SPEED_LIMIT_EXPLICIT",
      "clipname_video": "N/A",
      "state": "",
      "conditions": {
        "WeatherPrecipitation": [
          "PR_NO"
        ],
        "ConditionsLaneColor": [],
        "ConditionsRoadCategory": [
          "RC_HIGHWAY"
        ],
        "ConditionsRoadStructure": [],
        "WeatherCloudiness": [
          "CL_PARTIALLY_CLOUDY"
        ],
        "ConditionsRoadState": [
          "ROAD_DRY"
        ],
        "ConditionsRoadType": [
          "RT_PAVED"
        ],
        "WeatherLight": [
          "LI_DAY"
        ]
      },
      "type": "single",
      "frame_number": 14746
    },
    {
      "category": "Signs",
      "postion_coordinates": {
        "latitude": 25.100695554434488,
        "elevation": 73.33316040039062,
        "longitude": 121.75038845963546
      },
      "timestamp": 1663902584860599040,
      "clipnumber": -1,
      "label": "SIGN_SPECIAL_TSR",
      "clipname_video": "N/A",
      "state": "",
      "conditions": {
        "WeatherPrecipitation": [
          "PR_NO"
        ],
        "ConditionsLaneColor": [],
        "ConditionsRoadCategory": [
          "RC_HIGHWAY"
        ],
        "ConditionsRoadStructure": [],
        "WeatherCloudiness": [
          "CL_PARTIALLY_CLOUDY"
        ],
        "ConditionsRoadState": [
          "ROAD_DRY"
        ],
        "ConditionsRoadType": [
          "RT_PAVED"
        ],
        "WeatherLight": [
          "LI_DAY"
        ]
      },
      "type": "single",
      "frame_number": 14746
    },
    {
      "category": "Signs",
      "postion_coordinates": {
        "latitude": 25.102669615143252,
        "elevation": 67.75352478027344,
        "longitude": 121.75519929976078
      },
      "timestamp": 1663902621689552068,
      "clipnumber": -1,
      "label": "SIGN_SPEED_LIMIT_EXPLICIT",
      "clipname_video": "N/A",
      "state": "",
      "conditions": {
        "WeatherPrecipitation": [
          "PR_NO"
        ],
        "ConditionsLaneColor": [],
        "ConditionsRoadCategory": [
          "RC_HIGHWAY"
        ],
        "ConditionsRoadStructure": [],
        "WeatherCloudiness": [
          "CL_PARTIALLY_CLOUDY"
        ],
        "ConditionsRoadState": [
          "ROAD_DRY"
        ],
        "ConditionsRoadType": [
          "RT_PAVED"
        ],
        "WeatherLight": [
          "LI_DAY"
        ]
      },
      "type": "single",
      "frame_number": 16070
    },
    {
      "category": "Signs",
      "postion_coordinates": {
        "latitude": 25.103646365563687,
        "elevation": 64.3840103149414,
        "longitude": 121.75739116048443
      },
      "timestamp": 1663902638101568937,
      "clipnumber": -1,
      "label": "SIGN_WARNING",
      "clipname_video": "N/A",
      "state": "",
      "conditions": {
        "WeatherPrecipitation": [
          "PR_NO"
        ],
        "ConditionsLaneColor": [],
        "ConditionsRoadCategory": [
          "RC_HIGHWAY"
        ],
        "ConditionsRoadStructure": [],
        "WeatherCloudiness": [
          "CL_PARTIALLY_CLOUDY"
        ],
        "ConditionsRoadState": [
          "ROAD_DRY"
        ],
        "ConditionsRoadType": [
          "RT_PAVED"
        ],
        "WeatherLight": [
          "LI_DAY"
        ]
      },
      "type": "single",
      "frame_number": 16646
    },
    {
      "category": "ConditionsRoadEdge",
      "postion_coordinates": {
        "latitude": 25.10472628618396,
        "elevation": 71.07105255126953,
        "longitude": 121.75963582427725
      },
      "timestamp": 1663902656409540891,
      "clipnumber": -1,
      "label": "RE_CONCRETE_BARRIER",
      "clipname_video": "N/A",
      "state": "",
      "conditions": {
        "WeatherPrecipitation": [
          "PR_NO"
        ],
        "ConditionsLaneColor": [],
        "ConditionsRoadCategory": [
          "RC_HIGHWAY"
        ],
        "ConditionsRoadStructure": [],
        "WeatherCloudiness": [
          "CL_PARTIALLY_CLOUDY"
        ],
        "ConditionsRoadState": [
          "ROAD_DRY"
        ],
        "ConditionsRoadType": [
          "RT_PAVED"
        ],
        "WeatherLight": [
          "LI_DAY"
        ]
      },
      "type": "single",
      "frame_number": 17330
    },
    {
      "category": "VehicleManeuver",
      "postion_coordinates": {
        "latitude": 25.104931011482087,
        "elevation": 71.7273941040039,
        "longitude": 121.75987183053634
      },
      "timestamp": 1663902658739567041,
      "clipnumber": -1,
      "label": "LANE_CHANGE",
      "clipname_video": "N/A",
      "state": "",
      "conditions": {
        "WeatherPrecipitation": [
          "PR_NO"
        ],
        "ConditionsLaneColor": [],
        "ConditionsRoadCategory": [
          "RC_HIGHWAY"
        ],
        "ConditionsRoadStructure": [],
        "WeatherCloudiness": [
          "CL_PARTIALLY_CLOUDY"
        ],
        "ConditionsRoadState": [
          "ROAD_DRY"
        ],
        "ConditionsRoadType": [
          "RT_PAVED"
        ],
        "WeatherLight": [
          "LI_DAY"
        ]
      },
      "type": "single",
      "frame_number": 17405
    },
    {
      "category": "Signs",
      "postion_coordinates": {
        "latitude": 25.105626208383722,
        "elevation": 73.68961334228516,
        "longitude": 121.76038742616245
      },
      "timestamp": 1663902664709486961,
      "clipnumber": -1,
      "label": "SIGN_SPEED_LIMIT_EXPLICIT",
      "clipname_video": "N/A",
      "state": "",
      "conditions": {
        "WeatherPrecipitation": [
          "PR_NO"
        ],
        "ConditionsLaneColor": [],
        "ConditionsRoadCategory": [
          "RC_HIGHWAY"
        ],
        "ConditionsRoadStructure": [],
        "WeatherCloudiness": [
          "CL_PARTIALLY_CLOUDY"
        ],
        "ConditionsRoadState": [
          "ROAD_DRY"
        ],
        "ConditionsRoadType": [
          "RT_PAVED"
        ],
        "WeatherLight": [
          "LI_DAY"
        ]
      },
      "type": "single",
      "frame_number": 17620
    },
    {
      "category": "Signs",
      "postion_coordinates": {
        "latitude": 25.105695073238813,
        "elevation": 73.92335510253906,
        "longitude": 121.76042456652216
      },
      "timestamp": 1663902665049617052,
      "clipnumber": -1,
      "label": "SIGN_SUPPLEMENTARY",
      "clipname_video": "N/A",
      "state": "",
      "conditions": {
        "WeatherPrecipitation": [
          "PR_NO"
        ],
        "ConditionsLaneColor": [],
        "ConditionsRoadCategory": [
          "RC_HIGHWAY"
        ],
        "ConditionsRoadStructure": [],
        "WeatherCloudiness": [
          "CL_PARTIALLY_CLOUDY"
        ],
        "ConditionsRoadState": [
          "ROAD_DRY"
        ],
        "ConditionsRoadType": [
          "RT_PAVED"
        ],
        "WeatherLight": [
          "LI_DAY"
        ]
      },
      "type": "single",
      "frame_number": 17620
    },
    {
      "category": "Signs",
      "postion_coordinates": {
        "latitude": 25.107685872305446,
        "elevation": 80.13423919677734,
        "longitude": 121.76194505073698
      },
      "timestamp": 1663902682900156974,
      "clipnumber": -1,
      "label": "SIGN_WARNING",
      "clipname_video": "N/A",
      "state": "",
      "conditions": {
        "WeatherPrecipitation": [
          "PR_NO"
        ],
        "ConditionsLaneColor": [],
        "ConditionsRoadCategory": [
          "RC_HIGHWAY"
        ],
        "ConditionsRoadStructure": [],
        "WeatherCloudiness": [
          "CL_PARTIALLY_CLOUDY"
        ],
        "ConditionsRoadState": [
          "ROAD_DRY"
        ],
        "ConditionsRoadType": [
          "RT_PAVED"
        ],
        "WeatherLight": [
          "LI_DAY"
        ]
      },
      "type": "single",
      "frame_number": 18265
    },
    {
      "category": "Signs",
      "postion_coordinates": {
        "latitude": 25.107704029759617,
        "elevation": 80.28849029541016,
        "longitude": 121.76198575025214
      },
      "timestamp": 1663902683259524106,
      "clipnumber": -1,
      "label": "SIGN_SUPPLEMENTARY",
      "clipname_video": "N/A",
      "state": "",
      "conditions": {
        "WeatherPrecipitation": [
          "PR_NO"
        ],
        "ConditionsLaneColor": [],
        "ConditionsRoadCategory": [
          "RC_HIGHWAY"
        ],
        "ConditionsRoadStructure": [],
        "WeatherCloudiness": [
          "CL_PARTIALLY_CLOUDY"
        ],
        "ConditionsRoadState": [
          "ROAD_DRY"
        ],
        "ConditionsRoadType": [
          "RT_PAVED"
        ],
        "WeatherLight": [
          "LI_DAY"
        ]
      },
      "type": "single",
      "frame_number": 18304
    },
    {
      "category": "Signs",
      "postion_coordinates": {
        "latitude": 25.10781120926806,
        "elevation": 81.12930297851562,
        "longitude": 121.76227215084262
      },
      "timestamp": 1663902685389533996,
      "clipnumber": -1,
      "label": "SIGN_WARNING",
      "clipname_video": "N/A",
      "state": "",
      "conditions": {
        "WeatherPrecipitation": [
          "PR_NO"
        ],
        "ConditionsLaneColor": [],
        "ConditionsRoadCategory": [
          "RC_HIGHWAY"
        ],
        "ConditionsRoadStructure": [],
        "WeatherCloudiness": [
          "CL_PARTIALLY_CLOUDY"
        ],
        "ConditionsRoadState": [
          "ROAD_DRY"
        ],
        "ConditionsRoadType": [
          "RT_PAVED"
        ],
        "WeatherLight": [
          "LI_DAY"
        ]
      },
      "type": "single",
      "frame_number": 18374
    },
    {
      "category": "ConditionsRoadStructure",
      "postion_coordinates": {
        "latitude": 25.108171246782277,
        "elevation": 83.60942077636719,
        "longitude": 121.76342266334674
      },
      "timestamp": 1663902693740535974,
      "clipnumber": -1,
      "label": "RS_TUNNEL",
      "clipname_video": "N/A",
      "state": "activated",
      "conditions": {
        "WeatherPrecipitation": [
          "PR_NO"
        ],
        "ConditionsLaneColor": [],
        "ConditionsRoadCategory": [
          "RC_HIGHWAY"
        ],
        "ConditionsRoadStructure": [
          "RS_TUNNEL"
        ],
        "WeatherCloudiness": [
          "CL_PARTIALLY_CLOUDY"
        ],
        "ConditionsRoadState": [
          "ROAD_DRY"
        ],
        "ConditionsRoadType": [
          "RT_PAVED"
        ],
        "WeatherLight": [
          "LI_DAY"
        ]
      },
      "type": "multi-select",
      "frame_number": 18660
    },
    {
      "category": "WeatherLight",
      "postion_coordinates": {
        "latitude": 25.10820836751385,
        "elevation": 83.9034194946289,
        "longitude": 121.76354634917978
      },
      "timestamp": 1663902694639480113,
      "clipnumber": -1,
      "label": "LI_DAY",
      "clipname_video": "N/A",
      "state": "deactivated",
      "conditions": {
        "WeatherPrecipitation": [
          "PR_NO"
        ],
        "ConditionsLaneColor": [],
        "ConditionsRoadCategory": [
          "RC_HIGHWAY"
        ],
        "ConditionsRoadStructure": [
          "RS_TUNNEL"
        ],
        "WeatherCloudiness": [
          "CL_PARTIALLY_CLOUDY"
        ],
        "ConditionsRoadState": [
          "ROAD_DRY"
        ],
        "ConditionsRoadType": [
          "RT_PAVED"
        ],
        "WeatherLight": []
      },
      "type": "multi-select",
      "frame_number": 18699
    },
    {
      "category": "WeatherLight",
      "postion_coordinates": {
        "latitude": 25.10820836751385,
        "elevation": 83.9034194946289,
        "longitude": 121.76354634917978
      },
      "timestamp": 1663902694639480113,
      "clipnumber": -1,
      "label": "LI_ARTIFICIAL",
      "clipname_video": "N/A",
      "state": "activated",
      "conditions": {
        "WeatherPrecipitation": [
          "PR_NO"
        ],
        "ConditionsLaneColor": [],
        "ConditionsRoadCategory": [
          "RC_HIGHWAY"
        ],
        "ConditionsRoadStructure": [
          "RS_TUNNEL"
        ],
        "WeatherCloudiness": [
          "CL_PARTIALLY_CLOUDY"
        ],
        "ConditionsRoadState": [
          "ROAD_DRY"
        ],
        "ConditionsRoadType": [
          "RT_PAVED"
        ],
        "WeatherLight": [
          "LI_ARTIFICIAL"
        ]
      },
      "type": "multi-select",
      "frame_number": 18699
    },
    {
      "category": "ConditionsRoadStructure",
      "postion_coordinates": {
        "latitude": 25.10991540233364,
        "elevation": 89.81514739990234,
        "longitude": 121.76978634503993
      },
      "timestamp": 1663902737739690065,
      "clipnumber": -1,
      "label": "RS_TUNNEL",
      "clipname_video": "N/A",
      "state": "deactivated",
      "conditions": {
        "WeatherPrecipitation": [
          "PR_NO"
        ],
        "ConditionsLaneColor": [],
        "ConditionsRoadCategory": [
          "RC_HIGHWAY"
        ],
        "ConditionsRoadStructure": [],
        "WeatherCloudiness": [
          "CL_PARTIALLY_CLOUDY"
        ],
        "ConditionsRoadState": [
          "ROAD_DRY"
        ],
        "ConditionsRoadType": [
          "RT_PAVED"
        ],
        "WeatherLight": [
          "LI_ARTIFICIAL"
        ]
      },
      "type": "multi-select",
      "frame_number": 20250
    },
    {
      "category": "WeatherLight",
      "postion_coordinates": {
        "latitude": 25.109959503303685,
        "elevation": 89.48573303222656,
        "longitude": 121.7700207877463
      },
      "timestamp": 1663902739002016067,
      "clipnumber": -1,
      "label": "LI_ARTIFICIAL",
      "clipname_video": "N/A",
      "state": "deactivated",
      "conditions": {
        "WeatherPrecipitation": [
          "PR_NO"
        ],
        "ConditionsLaneColor": [],
        "ConditionsRoadCategory": [
          "RC_HIGHWAY"
        ],
        "ConditionsRoadStructure": [],
        "WeatherCloudiness": [
          "CL_PARTIALLY_CLOUDY"
        ],
        "ConditionsRoadState": [
          "ROAD_DRY"
        ],
        "ConditionsRoadType": [
          "RT_PAVED"
        ],
        "WeatherLight": []
      },
      "type": "multi-select",
      "frame_number": 20286
    },
    {
      "category": "WeatherLight",
      "postion_coordinates": {
        "latitude": 25.109959503303685,
        "elevation": 89.48573303222656,
        "longitude": 121.7700207877463
      },
      "timestamp": 1663902739002016067,
      "clipnumber": -1,
      "label": "LI_DAY",
      "clipname_video": "N/A",
      "state": "activated",
      "conditions": {
        "WeatherPrecipitation": [
          "PR_NO"
        ],
        "ConditionsLaneColor": [],
        "ConditionsRoadCategory": [
          "RC_HIGHWAY"
        ],
        "ConditionsRoadStructure": [],
        "WeatherCloudiness": [
          "CL_PARTIALLY_CLOUDY"
        ],
        "ConditionsRoadState": [
          "ROAD_DRY"
        ],
        "ConditionsRoadType": [
          "RT_PAVED"
        ],
        "WeatherLight": [
          "LI_DAY"
        ]
      },
      "type": "multi-select",
      "frame_number": 20286
    },
    {
      "category": "Signs",
      "postion_coordinates": {
        "latitude": 25.110072670467304,
        "elevation": 88.51447296142578,
        "longitude": 121.7706849208085
      },
      "timestamp": 1663902742729588031,
      "clipnumber": -1,
      "label": "SIGN_SPEED_LIMIT_EXPLICIT",
      "clipname_video": "N/A",
      "state": "",
      "conditions": {
        "WeatherPrecipitation": [
          "PR_NO"
        ],
        "ConditionsLaneColor": [],
        "ConditionsRoadCategory": [
          "RC_HIGHWAY"
        ],
        "ConditionsRoadStructure": [],
        "WeatherCloudiness": [
          "CL_PARTIALLY_CLOUDY"
        ],
        "ConditionsRoadState": [
          "ROAD_DRY"
        ],
        "ConditionsRoadType": [
          "RT_PAVED"
        ],
        "WeatherLight": [
          "LI_DAY"
        ]
      },
      "type": "single",
      "frame_number": 20432
    },
    {
      "category": "Signs",
      "postion_coordinates": {
        "latitude": 25.110080538381546,
        "elevation": 88.42762756347656,
        "longitude": 121.77073870505798
      },
      "timestamp": 1663902743061726093,
      "clipnumber": -1,
      "label": "SIGN_SPECIAL_TSR",
      "clipname_video": "N/A",
      "state": "",
      "conditions": {
        "WeatherPrecipitation": [
          "PR_NO"
        ],
        "ConditionsLaneColor": [],
        "ConditionsRoadCategory": [
          "RC_HIGHWAY"
        ],
        "ConditionsRoadStructure": [],
        "WeatherCloudiness": [
          "CL_PARTIALLY_CLOUDY"
        ],
        "ConditionsRoadState": [
          "ROAD_DRY"
        ],
        "ConditionsRoadType": [
          "RT_PAVED"
        ],
        "WeatherLight": [
          "LI_DAY"
        ]
      },
      "type": "single",
      "frame_number": 20432
    },
    {
      "category": "Signs",
      "postion_coordinates": {
        "latitude": 25.110406531824598,
        "elevation": 80.98773193359375,
        "longitude": 121.77471013753538
      },
      "timestamp": 1663902767489526033,
      "clipnumber": -1,
      "label": "SIGN_SPECIAL_TRAFFIC_LIGHT",
      "clipname_video": "N/A",
      "state": "",
      "conditions": {
        "WeatherPrecipitation": [
          "PR_NO"
        ],
        "ConditionsLaneColor": [],
        "ConditionsRoadCategory": [
          "RC_HIGHWAY"
        ],
        "ConditionsRoadStructure": [],
        "WeatherCloudiness": [
          "CL_PARTIALLY_CLOUDY"
        ],
        "ConditionsRoadState": [
          "ROAD_DRY"
        ],
        "ConditionsRoadType": [
          "RT_PAVED"
        ],
        "WeatherLight": [
          "LI_DAY"
        ]
      },
      "type": "single",
      "frame_number": 21330
    },
    {
      "category": "Signs",
      "postion_coordinates": {
        "latitude": 25.11041430797674,
        "elevation": 78.28265380859375,
        "longitude": 121.77784315247254
      },
      "timestamp": 1663902785459520101,
      "clipnumber": -1,
      "label": "SIGN_ELECTRONIC",
      "clipname_video": "N/A",
      "state": "",
      "conditions": {
        "WeatherPrecipitation": [
          "PR_NO"
        ],
        "ConditionsLaneColor": [],
        "ConditionsRoadCategory": [
          "RC_HIGHWAY"
        ],
        "ConditionsRoadStructure": [],
        "WeatherCloudiness": [
          "CL_PARTIALLY_CLOUDY"
        ],
        "ConditionsRoadState": [
          "ROAD_DRY"
        ],
        "ConditionsRoadType": [
          "RT_PAVED"
        ],
        "WeatherLight": [
          "LI_DAY"
        ]
      },
      "type": "single",
      "frame_number": 21970
    },
    {
      "category": "Signs",
      "postion_coordinates": {
        "latitude": 25.1104144845311,
        "elevation": 78.86483764648438,
        "longitude": 121.77821918427576
      },
      "timestamp": 1663902787579509019,
      "clipnumber": -1,
      "label": "SIGN_WARNING",
      "clipname_video": "N/A",
      "state": "",
      "conditions": {
        "WeatherPrecipitation": [
          "PR_NO"
        ],
        "ConditionsLaneColor": [],
        "ConditionsRoadCategory": [
          "RC_HIGHWAY"
        ],
        "ConditionsRoadStructure": [],
        "WeatherCloudiness": [
          "CL_PARTIALLY_CLOUDY"
        ],
        "ConditionsRoadState": [
          "ROAD_DRY"
        ],
        "ConditionsRoadType": [
          "RT_PAVED"
        ],
        "WeatherLight": [
          "LI_DAY"
        ]
      },
      "type": "single",
      "frame_number": 22044
    },
    {
      "category": "Signs",
      "postion_coordinates": {
        "latitude": 25.11041465948754,
        "elevation": 79.03140258789062,
        "longitude": 121.77832216639686
      },
      "timestamp": 1663902788069757938,
      "clipnumber": -1,
      "label": "SIGN_SPECIAL_TSR",
      "clipname_video": "N/A",
      "state": "",
      "conditions": {
        "WeatherPrecipitation": [
          "PR_NO"
        ],
        "ConditionsLaneColor": [],
        "ConditionsRoadCategory": [
          "RC_HIGHWAY"
        ],
        "ConditionsRoadStructure": [],
        "WeatherCloudiness": [
          "CL_PARTIALLY_CLOUDY"
        ],
        "ConditionsRoadState": [
          "ROAD_DRY"
        ],
        "ConditionsRoadType": [
          "RT_PAVED"
        ],
        "WeatherLight": [
          "LI_DAY"
        ]
      },
      "type": "single",
      "frame_number": 22044
    },
    {
      "category": "Signs",
      "postion_coordinates": {
        "latitude": 25.11041643190977,
        "elevation": 79.45588684082031,
        "longitude": 121.77854483494748
      },
      "timestamp": 1663902789509478092,
      "clipnumber": -1,
      "label": "SIGN_SPECIAL_TRAFFIC_LIGHT",
      "clipname_video": "N/A",
      "state": "",
      "conditions": {
        "WeatherPrecipitation": [
          "PR_NO"
        ],
        "ConditionsLaneColor": [],
        "ConditionsRoadCategory": [
          "RC_HIGHWAY"
        ],
        "ConditionsRoadStructure": [],
        "WeatherCloudiness": [
          "CL_PARTIALLY_CLOUDY"
        ],
        "ConditionsRoadState": [
          "ROAD_DRY"
        ],
        "ConditionsRoadType": [
          "RT_PAVED"
        ],
        "WeatherLight": [
          "LI_DAY"
        ]
      },
      "type": "single",
      "frame_number": 22117
    },
    {
      "category": "Signs",
      "postion_coordinates": {
        "latitude": 25.110418743847326,
        "elevation": 79.87564849853516,
        "longitude": 121.77878108425787
      },
      "timestamp": 1663902791023673057,
      "clipnumber": -1,
      "label": "SIGN_WARNING",
      "clipname_video": "N/A",
      "state": "",
      "conditions": {
        "WeatherPrecipitation": [
          "PR_NO"
        ],
        "ConditionsLaneColor": [],
        "ConditionsRoadCategory": [
          "RC_HIGHWAY"
        ],
        "ConditionsRoadStructure": [],
        "WeatherCloudiness": [
          "CL_PARTIALLY_CLOUDY"
        ],
        "ConditionsRoadState": [
          "ROAD_DRY"
        ],
        "ConditionsRoadType": [
          "RT_PAVED"
        ],
        "WeatherLight": [
          "LI_DAY"
        ]
      },
      "type": "single",
      "frame_number": 22156
    },
    {
      "category": "Signs",
      "postion_coordinates": {
        "latitude": 25.110420113665587,
        "elevation": 80.1584243774414,
        "longitude": 121.77893254585442
      },
      "timestamp": 1663902791769848108,
      "clipnumber": -1,
      "label": "SIGN_SUPPLEMENTARY",
      "clipname_video": "N/A",
      "state": "",
      "conditions": {
        "WeatherPrecipitation": [
          "PR_NO"
        ],
        "ConditionsLaneColor": [],
        "ConditionsRoadCategory": [
          "RC_HIGHWAY"
        ],
        "ConditionsRoadStructure": [],
        "WeatherCloudiness": [
          "CL_PARTIALLY_CLOUDY"
        ],
        "ConditionsRoadState": [
          "ROAD_DRY"
        ],
        "ConditionsRoadType": [
          "RT_PAVED"
        ],
        "WeatherLight": [
          "LI_DAY"
        ]
      },
      "type": "single",
      "frame_number": 22186
    },
    {
      "category": "Signs",
      "postion_coordinates": {
        "latitude": 25.11042060989817,
        "elevation": 80.5845947265625,
        "longitude": 121.77914825827432
      },
      "timestamp": 1663902793119508028,
      "clipnumber": -1,
      "label": "SIGN_PAVEMENT",
      "clipname_video": "N/A",
      "state": "",
      "conditions": {
        "WeatherPrecipitation": [
          "PR_NO"
        ],
        "ConditionsLaneColor": [],
        "ConditionsRoadCategory": [
          "RC_HIGHWAY"
        ],
        "ConditionsRoadStructure": [],
        "WeatherCloudiness": [
          "CL_PARTIALLY_CLOUDY"
        ],
        "ConditionsRoadState": [
          "ROAD_DRY"
        ],
        "ConditionsRoadType": [
          "RT_PAVED"
        ],
        "WeatherLight": [
          "LI_DAY"
        ]
      },
      "type": "single",
      "frame_number": 22230
    },
    {
      "category": "ConditionsRoadStructure",
      "postion_coordinates": {
        "latitude": 25.110421057950706,
        "elevation": 81.8852767944336,
        "longitude": 121.77973821657574
      },
      "timestamp": 1663902796820271968,
      "clipnumber": -1,
      "label": "RS_TUNNEL",
      "clipname_video": "N/A",
      "state": "activated",
      "conditions": {
        "WeatherPrecipitation": [
          "PR_NO"
        ],
        "ConditionsLaneColor": [],
        "ConditionsRoadCategory": [
          "RC_HIGHWAY"
        ],
        "ConditionsRoadStructure": [
          "RS_TUNNEL"
        ],
        "WeatherCloudiness": [
          "CL_PARTIALLY_CLOUDY"
        ],
        "ConditionsRoadState": [
          "ROAD_DRY"
        ],
        "ConditionsRoadType": [
          "RT_PAVED"
        ],
        "WeatherLight": [
          "LI_DAY"
        ]
      },
      "type": "multi-select",
      "frame_number": 22374
    },
    {
      "category": "WeatherLight",
      "postion_coordinates": {
        "latitude": 25.11042151641611,
        "elevation": 82.0967025756836,
        "longitude": 121.77983569523332
      },
      "timestamp": 1663902797569479942,
      "clipnumber": -1,
      "label": "LI_DAY",
      "clipname_video": "N/A",
      "state": "deactivated",
      "conditions": {
        "WeatherPrecipitation": [
          "PR_NO"
        ],
        "ConditionsLaneColor": [],
        "ConditionsRoadCategory": [
          "RC_HIGHWAY"
        ],
        "ConditionsRoadStructure": [
          "RS_TUNNEL"
        ],
        "WeatherCloudiness": [
          "CL_PARTIALLY_CLOUDY"
        ],
        "ConditionsRoadState": [
          "ROAD_DRY"
        ],
        "ConditionsRoadType": [
          "RT_PAVED"
        ],
        "WeatherLight": []
      },
      "type": "multi-select",
      "frame_number": 22412
    },
    {
      "category": "WeatherLight",
      "postion_coordinates": {
        "latitude": 25.11042151641611,
        "elevation": 82.0967025756836,
        "longitude": 121.77983569523332
      },
      "timestamp": 1663902797569479942,
      "clipnumber": -1,
      "label": "LI_ARTIFICIAL",
      "clipname_video": "N/A",
      "state": "activated",
      "conditions": {
        "WeatherPrecipitation": [
          "PR_NO"
        ],
        "ConditionsLaneColor": [],
        "ConditionsRoadCategory": [
          "RC_HIGHWAY"
        ],
        "ConditionsRoadStructure": [
          "RS_TUNNEL"
        ],
        "WeatherCloudiness": [
          "CL_PARTIALLY_CLOUDY"
        ],
        "ConditionsRoadState": [
          "ROAD_DRY"
        ],
        "ConditionsRoadType": [
          "RT_PAVED"
        ],
        "WeatherLight": [
          "LI_ARTIFICIAL"
        ]
      },
      "type": "multi-select",
      "frame_number": 22412
    },
    {
      "category": "ConditionsRoadStructure",
      "postion_coordinates": {
        "latitude": 25.110428956196348,
        "elevation": 88.23220825195312,
        "longitude": 121.78582157710294
      },
      "timestamp": 1663902838719532012,
      "clipnumber": -1,
      "label": "RS_TUNNEL",
      "clipname_video": "N/A",
      "state": "deactivated",
      "conditions": {
        "WeatherPrecipitation": [
          "PR_NO"
        ],
        "ConditionsLaneColor": [],
        "ConditionsRoadCategory": [
          "RC_HIGHWAY"
        ],
        "ConditionsRoadStructure": [],
        "WeatherCloudiness": [
          "CL_PARTIALLY_CLOUDY"
        ],
        "ConditionsRoadState": [
          "ROAD_DRY"
        ],
        "ConditionsRoadType": [
          "RT_PAVED"
        ],
        "WeatherLight": [
          "LI_ARTIFICIAL"
        ]
      },
      "type": "multi-select",
      "frame_number": 23888
    },
    {
      "category": "WeatherLight",
      "postion_coordinates": {
        "latitude": 25.110441554253363,
        "elevation": 88.1376953125,
        "longitude": 121.78599855573196
      },
      "timestamp": 1663902840021028995,
      "clipnumber": -1,
      "label": "LI_ARTIFICIAL",
      "clipname_video": "N/A",
      "state": "deactivated",
      "conditions": {
        "WeatherPrecipitation": [
          "PR_NO"
        ],
        "ConditionsLaneColor": [],
        "ConditionsRoadCategory": [
          "RC_HIGHWAY"
        ],
        "ConditionsRoadStructure": [],
        "WeatherCloudiness": [
          "CL_PARTIALLY_CLOUDY"
        ],
        "ConditionsRoadState": [
          "ROAD_DRY"
        ],
        "ConditionsRoadType": [
          "RT_PAVED"
        ],
        "WeatherLight": []
      },
      "type": "multi-select",
      "frame_number": 23924
    },
    {
      "category": "WeatherLight",
      "postion_coordinates": {
        "latitude": 25.110441554253363,
        "elevation": 88.1376953125,
        "longitude": 121.78599855573196
      },
      "timestamp": 1663902840021028995,
      "clipnumber": -1,
      "label": "LI_DAY",
      "clipname_video": "N/A",
      "state": "activated",
      "conditions": {
        "WeatherPrecipitation": [
          "PR_NO"
        ],
        "ConditionsLaneColor": [],
        "ConditionsRoadCategory": [
          "RC_HIGHWAY"
        ],
        "ConditionsRoadStructure": [],
        "WeatherCloudiness": [
          "CL_PARTIALLY_CLOUDY"
        ],
        "ConditionsRoadState": [
          "ROAD_DRY"
        ],
        "ConditionsRoadType": [
          "RT_PAVED"
        ],
        "WeatherLight": [
          "LI_DAY"
        ]
      },
      "type": "multi-select",
      "frame_number": 23924
    },
    {
      "category": "OddObject",
      "postion_coordinates": {
        "latitude": 25.11048331616535,
        "elevation": 87.86009979248047,
        "longitude": 121.7862592078304
      },
      "timestamp": 1663902842339488983,
      "clipnumber": -1,
      "label": "OO_GENERAL_OBJ_VEHICLES",
      "clipname_video": "N/A",
      "state": "",
      "conditions": {
        "WeatherPrecipitation": [
          "PR_NO"
        ],
        "ConditionsLaneColor": [],
        "ConditionsRoadCategory": [
          "RC_HIGHWAY"
        ],
        "ConditionsRoadStructure": [],
        "WeatherCloudiness": [
          "CL_PARTIALLY_CLOUDY"
        ],
        "ConditionsRoadState": [
          "ROAD_DRY"
        ],
        "ConditionsRoadType": [
          "RT_PAVED"
        ],
        "WeatherLight": [
          "LI_DAY"
        ]
      },
      "type": "single",
      "frame_number": 24030
    },
    {
      "category": "Signs",
      "postion_coordinates": {
        "latitude": 25.11242160765624,
        "elevation": 86.40949249267578,
        "longitude": 121.78947653375472
      },
      "timestamp": 1663902867020112991,
      "clipnumber": -1,
      "label": "SIGN_OTHER",
      "clipname_video": "N/A",
      "state": "",
      "conditions": {
        "WeatherPrecipitation": [
          "PR_NO"
        ],
        "ConditionsLaneColor": [],
        "ConditionsRoadCategory": [
          "RC_HIGHWAY"
        ],
        "ConditionsRoadStructure": [],
        "WeatherCloudiness": [
          "CL_PARTIALLY_CLOUDY"
        ],
        "ConditionsRoadState": [
          "ROAD_DRY"
        ],
        "ConditionsRoadType": [
          "RT_PAVED"
        ],
        "WeatherLight": [
          "LI_DAY"
        ]
      },
      "type": "single",
      "frame_number": 24898
    },
    {
      "category": "Signs",
      "postion_coordinates": {
        "latitude": 25.11296035360903,
        "elevation": 86.66354370117188,
        "longitude": 121.7902291879861
      },
      "timestamp": 1663902873569542884,
      "clipnumber": -1,
      "label": "SIGN_OTHER",
      "clipname_video": "N/A",
      "state": "",
      "conditions": {
        "WeatherPrecipitation": [
          "PR_NO"
        ],
        "ConditionsLaneColor": [],
        "ConditionsRoadCategory": [
          "RC_HIGHWAY"
        ],
        "ConditionsRoadStructure": [],
        "WeatherCloudiness": [
          "CL_PARTIALLY_CLOUDY"
        ],
        "ConditionsRoadState": [
          "ROAD_DRY"
        ],
        "ConditionsRoadType": [
          "RT_PAVED"
        ],
        "WeatherLight": [
          "LI_DAY"
        ]
      },
      "type": "single",
      "frame_number": 25136
    },
    {
      "category": "Signs",
      "postion_coordinates": {
        "latitude": 25.113199059596003,
        "elevation": 86.76500701904297,
        "longitude": 121.79067655838828
      },
      "timestamp": 1663902876810682058,
      "clipnumber": -1,
      "label": "SIGN_OTHER",
      "clipname_video": "N/A",
      "state": "",
      "conditions": {
        "WeatherPrecipitation": [
          "PR_NO"
        ],
        "ConditionsLaneColor": [],
        "ConditionsRoadCategory": [
          "RC_HIGHWAY"
        ],
        "ConditionsRoadStructure": [],
        "WeatherCloudiness": [
          "CL_PARTIALLY_CLOUDY"
        ],
        "ConditionsRoadState": [
          "ROAD_DRY"
        ],
        "ConditionsRoadType": [
          "RT_PAVED"
        ],
        "WeatherLight": [
          "LI_DAY"
        ]
      },
      "type": "single",
      "frame_number": 25248
    },
    {
      "category": "Signs",
      "postion_coordinates": {
        "latitude": 25.113490958648057,
        "elevation": 86.38320922851562,
        "longitude": 121.7918990098609
      },
      "timestamp": 1663902884900589942,
      "clipnumber": -1,
      "label": "SIGN_PAVEMENT",
      "clipname_video": "N/A",
      "state": "",
      "conditions": {
        "WeatherPrecipitation": [
          "PR_NO"
        ],
        "ConditionsLaneColor": [],
        "ConditionsRoadCategory": [
          "RC_HIGHWAY"
        ],
        "ConditionsRoadStructure": [],
        "WeatherCloudiness": [
          "CL_PARTIALLY_CLOUDY"
        ],
        "ConditionsRoadState": [
          "ROAD_DRY"
        ],
        "ConditionsRoadType": [
          "RT_PAVED"
        ],
        "WeatherLight": [
          "LI_DAY"
        ]
      },
      "type": "single",
      "frame_number": 25540
    },
    {
      "category": "Signs",
      "postion_coordinates": {
        "latitude": 25.113661525515443,
        "elevation": 81.50331115722656,
        "longitude": 121.79466643031017
      },
      "timestamp": 1663902908959558010,
      "clipnumber": -1,
      "label": "SIGN_WARNING",
      "clipname_video": "N/A",
      "state": "",
      "conditions": {
        "WeatherPrecipitation": [
          "PR_NO"
        ],
        "ConditionsLaneColor": [],
        "ConditionsRoadCategory": [
          "RC_HIGHWAY"
        ],
        "ConditionsRoadStructure": [],
        "WeatherCloudiness": [
          "CL_PARTIALLY_CLOUDY"
        ],
        "ConditionsRoadState": [
          "ROAD_DRY"
        ],
        "ConditionsRoadType": [
          "RT_PAVED"
        ],
        "WeatherLight": [
          "LI_DAY"
        ]
      },
      "type": "single",
      "frame_number": 26389
    },
    {
      "category": "Signs",
      "postion_coordinates": {
        "latitude": 25.113162259097344,
        "elevation": 79.28091430664062,
        "longitude": 121.79512777965
      },
      "timestamp": 1663902915611943960,
      "clipnumber": -1,
      "label": "SIGN_WARNING",
      "clipname_video": "N/A",
      "state": "",
      "conditions": {
        "WeatherPrecipitation": [
          "PR_NO"
        ],
        "ConditionsLaneColor": [],
        "ConditionsRoadCategory": [
          "RC_HIGHWAY"
        ],
        "ConditionsRoadStructure": [],
        "WeatherCloudiness": [
          "CL_PARTIALLY_CLOUDY"
        ],
        "ConditionsRoadState": [
          "ROAD_DRY"
        ],
        "ConditionsRoadType": [
          "RT_PAVED"
        ],
        "WeatherLight": [
          "LI_DAY"
        ]
      },
      "type": "single",
      "frame_number": 26652
    },
    {
      "category": "Signs",
      "postion_coordinates": {
        "latitude": 25.1130890537304,
        "elevation": 78.69355010986328,
        "longitude": 121.79521410474214
      },
      "timestamp": 1663902916761648893,
      "clipnumber": -1,
      "label": "SIGN_SPEED_LIMIT_EXPLICIT",
      "clipname_video": "N/A",
      "state": "",
      "conditions": {
        "WeatherPrecipitation": [
          "PR_NO"
        ],
        "ConditionsLaneColor": [],
        "ConditionsRoadCategory": [
          "RC_HIGHWAY"
        ],
        "ConditionsRoadStructure": [],
        "WeatherCloudiness": [
          "CL_PARTIALLY_CLOUDY"
        ],
        "ConditionsRoadState": [
          "ROAD_DRY"
        ],
        "ConditionsRoadType": [
          "RT_PAVED"
        ],
        "WeatherLight": [
          "LI_DAY"
        ]
      },
      "type": "single",
      "frame_number": 26688
    },
    {
      "category": "Signs",
      "postion_coordinates": {
        "latitude": 25.113070848589935,
        "elevation": 78.50606536865234,
        "longitude": 121.79523918908187
      },
      "timestamp": 1663902917013740062,
      "clipnumber": -1,
      "label": "SIGN_SUPPLEMENTARY",
      "clipname_video": "N/A",
      "state": "",
      "conditions": {
        "WeatherPrecipitation": [
          "PR_NO"
        ],
        "ConditionsLaneColor": [],
        "ConditionsRoadCategory": [
          "RC_HIGHWAY"
        ],
        "ConditionsRoadStructure": [],
        "WeatherCloudiness": [
          "CL_PARTIALLY_CLOUDY"
        ],
        "ConditionsRoadState": [
          "ROAD_DRY"
        ],
        "ConditionsRoadType": [
          "RT_PAVED"
        ],
        "WeatherLight": [
          "LI_DAY"
        ]
      },
      "type": "single",
      "frame_number": 26688
    },
    {
      "category": "Signs",
      "postion_coordinates": {
        "latitude": 25.112989561711455,
        "elevation": 77.38583374023438,
        "longitude": 121.79537972648386
      },
      "timestamp": 1663902918639465093,
      "clipnumber": -1,
      "label": "SIGN_SPEED_LIMIT_EXPLICIT",
      "clipname_video": "N/A",
      "state": "",
      "conditions": {
        "WeatherPrecipitation": [
          "PR_NO"
        ],
        "ConditionsLaneColor": [],
        "ConditionsRoadCategory": [
          "RC_HIGHWAY"
        ],
        "ConditionsRoadStructure": [],
        "WeatherCloudiness": [
          "CL_PARTIALLY_CLOUDY"
        ],
        "ConditionsRoadState": [
          "ROAD_DRY"
        ],
        "ConditionsRoadType": [
          "RT_PAVED"
        ],
        "WeatherLight": [
          "LI_DAY"
        ]
      },
      "type": "single",
      "frame_number": 26760
    },
    {
      "category": "Signs",
      "postion_coordinates": {
        "latitude": 25.112900563976723,
        "elevation": 75.1307601928711,
        "longitude": 121.79563028272207
      },
      "timestamp": 1663902921199486970,
      "clipnumber": -1,
      "label": "SIGN_WARNING",
      "clipname_video": "N/A",
      "state": "",
      "conditions": {
        "WeatherPrecipitation": [
          "PR_NO"
        ],
        "ConditionsLaneColor": [],
        "ConditionsRoadCategory": [
          "RC_HIGHWAY"
        ],
        "ConditionsRoadStructure": [],
        "WeatherCloudiness": [
          "CL_PARTIALLY_CLOUDY"
        ],
        "ConditionsRoadState": [
          "ROAD_DRY"
        ],
        "ConditionsRoadType": [
          "RT_PAVED"
        ],
        "WeatherLight": [
          "LI_DAY"
        ]
      },
      "type": "single",
      "frame_number": 26862
    },
    {
      "category": "Signs",
      "postion_coordinates": {
        "latitude": 25.112890445106295,
        "elevation": 74.81587219238281,
        "longitude": 121.79566499779072
      },
      "timestamp": 1663902921559478044,
      "clipnumber": -1,
      "label": "SIGN_SUPPLEMENTARY",
      "clipname_video": "N/A",
      "state": "",
      "conditions": {
        "WeatherPrecipitation": [
          "PR_NO"
        ],
        "ConditionsLaneColor": [],
        "ConditionsRoadCategory": [
          "RC_HIGHWAY"
        ],
        "ConditionsRoadStructure": [],
        "WeatherCloudiness": [
          "CL_PARTIALLY_CLOUDY"
        ],
        "ConditionsRoadState": [
          "ROAD_DRY"
        ],
        "ConditionsRoadType": [
          "RT_PAVED"
        ],
        "WeatherLight": [
          "LI_DAY"
        ]
      },
      "type": "single",
      "frame_number": 26862
    },
    {
      "category": "Signs",
      "postion_coordinates": {
        "latitude": 25.112815772935566,
        "elevation": 72.55865478515625,
        "longitude": 121.79593823911071
      },
      "timestamp": 1663902923659514904,
      "clipnumber": -1,
      "label": "SIGN_WARNING",
      "clipname_video": "N/A",
      "state": "",
      "conditions": {
        "WeatherPrecipitation": [
          "PR_NO"
        ],
        "ConditionsLaneColor": [],
        "ConditionsRoadCategory": [
          "RC_HIGHWAY"
        ],
        "ConditionsRoadStructure": [],
        "WeatherCloudiness": [
          "CL_PARTIALLY_CLOUDY"
        ],
        "ConditionsRoadState": [
          "ROAD_DRY"
        ],
        "ConditionsRoadType": [
          "RT_PAVED"
        ],
        "WeatherLight": [
          "LI_DAY"
        ]
      },
      "type": "single",
      "frame_number": 26938
    },
    {
      "category": "Signs",
      "postion_coordinates": {
        "latitude": 25.112801743653815,
        "elevation": 72.40196990966797,
        "longitude": 121.79598802850094
      },
      "timestamp": 1663902924089512109,
      "clipnumber": -1,
      "label": "SIGN_WARNING",
      "clipname_video": "N/A",
      "state": "",
      "conditions": {
        "WeatherPrecipitation": [
          "PR_NO"
        ],
        "ConditionsLaneColor": [],
        "ConditionsRoadCategory": [
          "RC_HIGHWAY"
        ],
        "ConditionsRoadStructure": [],
        "WeatherCloudiness": [
          "CL_PARTIALLY_CLOUDY"
        ],
        "ConditionsRoadState": [
          "ROAD_DRY"
        ],
        "ConditionsRoadType": [
          "RT_PAVED"
        ],
        "WeatherLight": [
          "LI_DAY"
        ]
      },
      "type": "single",
      "frame_number": 26938
    },
    {
      "category": "Signs",
      "postion_coordinates": {
        "latitude": 25.112788467036157,
        "elevation": 72.31277465820312,
        "longitude": 121.79603459317347
      },
      "timestamp": 1663902924489559888,
      "clipnumber": -1,
      "label": "SIGN_WARNING",
      "clipname_video": "N/A",
      "state": "",
      "conditions": {
        "WeatherPrecipitation": [
          "PR_NO"
        ],
        "ConditionsLaneColor": [],
        "ConditionsRoadCategory": [
          "RC_HIGHWAY"
        ],
        "ConditionsRoadStructure": [],
        "WeatherCloudiness": [
          "CL_PARTIALLY_CLOUDY"
        ],
        "ConditionsRoadState": [
          "ROAD_DRY"
        ],
        "ConditionsRoadType": [
          "RT_PAVED"
        ],
        "WeatherLight": [
          "LI_DAY"
        ]
      },
      "type": "single",
      "frame_number": 26975
    },
    {
      "category": "ConditionsRoadCategory",
      "postion_coordinates": {
        "latitude": 25.11268040626209,
        "elevation": 72.3006362915039,
        "longitude": 121.79642305966877
      },
      "timestamp": 1663902928359523057,
      "clipnumber": -1,
      "label": "RC_HIGHWAY",
      "clipname_video": "N/A",
      "state": "deactivated",
      "conditions": {
        "WeatherPrecipitation": [
          "PR_NO"
        ],
        "ConditionsLaneColor": [],
        "ConditionsRoadCategory": [],
        "ConditionsRoadStructure": [],
        "WeatherCloudiness": [
          "CL_PARTIALLY_CLOUDY"
        ],
        "ConditionsRoadState": [
          "ROAD_DRY"
        ],
        "ConditionsRoadType": [
          "RT_PAVED"
        ],
        "WeatherLight": [
          "LI_DAY"
        ]
      },
      "type": "multi-select",
      "frame_number": 27123
    },
    {
      "category": "ConditionsRoadCategory",
      "postion_coordinates": {
        "latitude": 25.11268040626209,
        "elevation": 72.3006362915039,
        "longitude": 121.79642305966877
      },
      "timestamp": 1663902928359523057,
      "clipnumber": -1,
      "label": "RC_COUNTRY_ROADS",
      "clipname_video": "N/A",
      "state": "activated",
      "conditions": {
        "WeatherPrecipitation": [
          "PR_NO"
        ],
        "ConditionsLaneColor": [],
        "ConditionsRoadCategory": [
          "RC_COUNTRY_ROADS"
        ],
        "ConditionsRoadStructure": [],
        "WeatherCloudiness": [
          "CL_PARTIALLY_CLOUDY"
        ],
        "ConditionsRoadState": [
          "ROAD_DRY"
        ],
        "ConditionsRoadType": [
          "RT_PAVED"
        ],
        "WeatherLight": [
          "LI_DAY"
        ]
      },
      "type": "multi-select",
      "frame_number": 27123
    },
    {
      "category": "ConditionsLaneColor",
      "postion_coordinates": {
        "latitude": 25.112479472080153,
        "elevation": 69.50067901611328,
        "longitude": 121.79737121307085
      },
      "timestamp": 1663902939319590091,
      "clipnumber": -1,
      "label": "LC_YELLOW_BLUE",
      "clipname_video": "N/A",
      "state": "activated",
      "conditions": {
        "WeatherPrecipitation": [
          "PR_NO"
        ],
        "ConditionsLaneColor": [
          "LC_YELLOW_BLUE"
        ],
        "ConditionsRoadCategory": [
          "RC_COUNTRY_ROADS"
        ],
        "ConditionsRoadStructure": [],
        "WeatherCloudiness": [
          "CL_PARTIALLY_CLOUDY"
        ],
        "ConditionsRoadState": [
          "ROAD_DRY"
        ],
        "ConditionsRoadType": [
          "RT_PAVED"
        ],
        "WeatherLight": [
          "LI_DAY"
        ]
      },
      "type": "multi-select",
      "frame_number": 27516
    },
    {
      "category": "ConditionsLaneColor",
      "postion_coordinates": {
        "latitude": 25.11074725049301,
        "elevation": 73.23344421386719,
        "longitude": 121.80093270455762
      },
      "timestamp": 1663902978429526090,
      "clipnumber": -1,
      "label": "LC_YELLOW_BLUE",
      "clipname_video": "N/A",
      "state": "deactivated",
      "conditions": {
        "WeatherPrecipitation": [
          "PR_NO"
        ],
        "ConditionsLaneColor": [],
        "ConditionsRoadCategory": [
          "RC_COUNTRY_ROADS"
        ],
        "ConditionsRoadStructure": [],
        "WeatherCloudiness": [
          "CL_PARTIALLY_CLOUDY"
        ],
        "ConditionsRoadState": [
          "ROAD_DRY"
        ],
        "ConditionsRoadType": [
          "RT_PAVED"
        ],
        "WeatherLight": [
          "LI_DAY"
        ]
      },
      "type": "multi-select",
      "frame_number": 28926
    },
    {
      "category": "ConditionsLaneColor",
      "postion_coordinates": {
        "latitude": 25.110733537894728,
        "elevation": 73.29067993164062,
        "longitude": 121.8009560951825
      },
      "timestamp": 1663902978689513921,
      "clipnumber": -1,
      "label": "LC_RED_GREEN_ORANGE",
      "clipname_video": "N/A",
      "state": "activated",
      "conditions": {
        "WeatherPrecipitation": [
          "PR_NO"
        ],
        "ConditionsLaneColor": [
          "LC_RED_GREEN_ORANGE"
        ],
        "ConditionsRoadCategory": [
          "RC_COUNTRY_ROADS"
        ],
        "ConditionsRoadStructure": [],
        "WeatherCloudiness": [
          "CL_PARTIALLY_CLOUDY"
        ],
        "ConditionsRoadState": [
          "ROAD_DRY"
        ],
        "ConditionsRoadType": [
          "RT_PAVED"
        ],
        "WeatherLight": [
          "LI_DAY"
        ]
      },
      "type": "multi-select",
      "frame_number": 28926
    },
    {
      "category": "Signs",
      "postion_coordinates": {
        "latitude": 25.10971642450743,
        "elevation": 74.36857604980469,
        "longitude": 121.80263501878476
      },
      "timestamp": 1663902997139528036,
      "clipnumber": -1,
      "label": "SIGN_WARNING",
      "clipname_video": "N/A",
      "state": "",
      "conditions": {
        "WeatherPrecipitation": [
          "PR_NO"
        ],
        "ConditionsLaneColor": [
          "LC_RED_GREEN_ORANGE"
        ],
        "ConditionsRoadCategory": [
          "RC_COUNTRY_ROADS"
        ],
        "ConditionsRoadStructure": [],
        "WeatherCloudiness": [
          "CL_PARTIALLY_CLOUDY"
        ],
        "ConditionsRoadState": [
          "ROAD_DRY"
        ],
        "ConditionsRoadType": [
          "RT_PAVED"
        ],
        "WeatherLight": [
          "LI_DAY"
        ]
      },
      "type": "single",
      "frame_number": 29604
    },
    {
      "category": "Signs",
      "postion_coordinates": {
        "latitude": 25.109100095966678,
        "elevation": 72.52336883544922,
        "longitude": 121.8033998228721
      },
      "timestamp": 1663903007920489072,
      "clipnumber": -1,
      "label": "SIGN_WARNING",
      "clipname_video": "N/A",
      "state": "",
      "conditions": {
        "WeatherPrecipitation": [
          "PR_NO"
        ],
        "ConditionsLaneColor": [
          "LC_RED_GREEN_ORANGE"
        ],
        "ConditionsRoadCategory": [
          "RC_COUNTRY_ROADS"
        ],
        "ConditionsRoadStructure": [],
        "WeatherCloudiness": [
          "CL_PARTIALLY_CLOUDY"
        ],
        "ConditionsRoadState": [
          "ROAD_DRY"
        ],
        "ConditionsRoadType": [
          "RT_PAVED"
        ],
        "WeatherLight": [
          "LI_DAY"
        ]
      },
      "type": "single",
      "frame_number": 29966
    },
    {
      "category": "Signs",
      "postion_coordinates": {
        "latitude": 25.10907462895205,
        "elevation": 72.45606994628906,
        "longitude": 121.80342847710106
      },
      "timestamp": 1663903008459558010,
      "clipnumber": -1,
      "label": "SIGN_SUPPLEMENTARY",
      "clipname_video": "N/A",
      "state": "",
      "conditions": {
        "WeatherPrecipitation": [
          "PR_NO"
        ],
        "ConditionsLaneColor": [
          "LC_RED_GREEN_ORANGE"
        ],
        "ConditionsRoadCategory": [
          "RC_COUNTRY_ROADS"
        ],
        "ConditionsRoadStructure": [],
        "WeatherCloudiness": [
          "CL_PARTIALLY_CLOUDY"
        ],
        "ConditionsRoadState": [
          "ROAD_DRY"
        ],
        "ConditionsRoadType": [
          "RT_PAVED"
        ],
        "WeatherLight": [
          "LI_DAY"
        ]
      },
      "type": "single",
      "frame_number": 30006
    },
    {
      "category": "Signs",
      "postion_coordinates": {
        "latitude": 25.10824727952511,
        "elevation": 72.59362030029297,
        "longitude": 121.80569314861468
      },
      "timestamp": 1663903047249516963,
      "clipnumber": -1,
      "label": "SIGN_WARNING",
      "clipname_video": "N/A",
      "state": "",
      "conditions": {
        "WeatherPrecipitation": [
          "PR_NO"
        ],
        "ConditionsLaneColor": [
          "LC_RED_GREEN_ORANGE"
        ],
        "ConditionsRoadCategory": [
          "RC_COUNTRY_ROADS"
        ],
        "ConditionsRoadStructure": [],
        "WeatherCloudiness": [
          "CL_PARTIALLY_CLOUDY"
        ],
        "ConditionsRoadState": [
          "ROAD_DRY"
        ],
        "ConditionsRoadType": [
          "RT_PAVED"
        ],
        "WeatherLight": [
          "LI_DAY"
        ]
      },
      "type": "single",
      "frame_number": 31408
    },
    {
      "category": "OddObject",
      "postion_coordinates": {
        "latitude": 25.10802415267858,
        "elevation": 72.29867553710938,
        "longitude": 121.8066429667623
      },
      "timestamp": 1663903062729545116,
      "clipnumber": -1,
      "label": "OO_GENERAL_OBJ_HUMANS",
      "clipname_video": "N/A",
      "state": "",
      "conditions": {
        "WeatherPrecipitation": [
          "PR_NO"
        ],
        "ConditionsLaneColor": [
          "LC_RED_GREEN_ORANGE"
        ],
        "ConditionsRoadCategory": [
          "RC_COUNTRY_ROADS"
        ],
        "ConditionsRoadStructure": [],
        "WeatherCloudiness": [
          "CL_PARTIALLY_CLOUDY"
        ],
        "ConditionsRoadState": [
          "ROAD_DRY"
        ],
        "ConditionsRoadType": [
          "RT_PAVED"
        ],
        "WeatherLight": [
          "LI_DAY"
        ]
      },
      "type": "single",
      "frame_number": 31944
    },
    {
      "category": "VariousEvents",
      "postion_coordinates": {
        "latitude": 25.107707643896063,
        "elevation": 71.72216796875,
        "longitude": 121.80805553375716
      },
      "timestamp": 1663903084599488019,
      "clipnumber": -1,
      "label": "EV_PEDESTRIAN_GROUP",
      "clipname_video": "N/A",
      "state": "",
      "conditions": {
        "WeatherPrecipitation": [
          "PR_NO"
        ],
        "ConditionsLaneColor": [
          "LC_RED_GREEN_ORANGE"
        ],
        "ConditionsRoadCategory": [
          "RC_COUNTRY_ROADS"
        ],
        "ConditionsRoadStructure": [],
        "WeatherCloudiness": [
          "CL_PARTIALLY_CLOUDY"
        ],
        "ConditionsRoadState": [
          "ROAD_DRY"
        ],
        "ConditionsRoadType": [
          "RT_PAVED"
        ],
        "WeatherLight": [
          "LI_DAY"
        ]
      },
      "type": "single",
      "frame_number": 32724
    },
    {
      "category": "VariousEvents",
      "postion_coordinates": {
        "latitude": 25.107705393725663,
        "elevation": 71.82788848876953,
        "longitude": 121.80806250213946
      },
      "timestamp": 1663903085149552106,
      "clipnumber": -1,
      "label": "EV_PEDESTRIAN_GROUP",
      "clipname_video": "N/A",
      "state": "",
      "conditions": {
        "WeatherPrecipitation": [
          "PR_NO"
        ],
        "ConditionsLaneColor": [
          "LC_RED_GREEN_ORANGE"
        ],
        "ConditionsRoadCategory": [
          "RC_COUNTRY_ROADS"
        ],
        "ConditionsRoadStructure": [],
        "WeatherCloudiness": [
          "CL_PARTIALLY_CLOUDY"
        ],
        "ConditionsRoadState": [
          "ROAD_DRY"
        ],
        "ConditionsRoadType": [
          "RT_PAVED"
        ],
        "WeatherLight": [
          "LI_DAY"
        ]
      },
      "type": "single",
      "frame_number": 32753
    },
    {
      "category": "ConditionsRoadState",
      "postion_coordinates": {
        "latitude": 25.107694786688686,
        "elevation": 72.0830078125,
        "longitude": 121.8080967108547
      },
      "timestamp": 1663903086289489030,
      "clipnumber": -1,
      "label": "ROAD_DRY",
      "clipname_video": "N/A",
      "state": "deactivated",
      "conditions": {
        "WeatherPrecipitation": [
          "PR_NO"
        ],
        "ConditionsLaneColor": [
          "LC_RED_GREEN_ORANGE"
        ],
        "ConditionsRoadCategory": [
          "RC_COUNTRY_ROADS"
        ],
        "ConditionsRoadStructure": [],
        "WeatherCloudiness": [
          "CL_PARTIALLY_CLOUDY"
        ],
        "ConditionsRoadState": [],
        "ConditionsRoadType": [
          "RT_PAVED"
        ],
        "WeatherLight": [
          "LI_DAY"
        ]
      },
      "type": "multi-select",
      "frame_number": 32804
    },
    {
      "category": "ConditionsRoadState",
      "postion_coordinates": {
        "latitude": 25.107694786688686,
        "elevation": 72.0830078125,
        "longitude": 121.8080967108547
      },
      "timestamp": 1663903086289489030,
      "clipnumber": -1,
      "label": "ROAD_ICE",
      "clipname_video": "N/A",
      "state": "activated",
      "conditions": {
        "WeatherPrecipitation": [
          "PR_NO"
        ],
        "ConditionsLaneColor": [
          "LC_RED_GREEN_ORANGE"
        ],
        "ConditionsRoadCategory": [
          "RC_COUNTRY_ROADS"
        ],
        "ConditionsRoadStructure": [],
        "WeatherCloudiness": [
          "CL_PARTIALLY_CLOUDY"
        ],
        "ConditionsRoadState": [
          "ROAD_ICE"
        ],
        "ConditionsRoadType": [
          "RT_PAVED"
        ],
        "WeatherLight": [
          "LI_DAY"
        ]
      },
      "type": "multi-select",
      "frame_number": 32804
    },
    {
      "category": "ConditionsRoadState",
      "postion_coordinates": {
        "latitude": 25.107675110728824,
        "elevation": 72.13245391845703,
        "longitude": 121.8081745560618
      },
      "timestamp": 1663903088299479007,
      "clipnumber": -1,
      "label": "ROAD_ICE",
      "clipname_video": "N/A",
      "state": "deactivated",
      "conditions": {
        "WeatherPrecipitation": [
          "PR_NO"
        ],
        "ConditionsLaneColor": [
          "LC_RED_GREEN_ORANGE"
        ],
        "ConditionsRoadCategory": [
          "RC_COUNTRY_ROADS"
        ],
        "ConditionsRoadStructure": [],
        "WeatherCloudiness": [
          "CL_PARTIALLY_CLOUDY"
        ],
        "ConditionsRoadState": [],
        "ConditionsRoadType": [
          "RT_PAVED"
        ],
        "WeatherLight": [
          "LI_DAY"
        ]
      },
      "type": "multi-select",
      "frame_number": 32878
    },
    {
      "category": "ConditionsRoadState",
      "postion_coordinates": {
        "latitude": 25.107675110728824,
        "elevation": 72.13245391845703,
        "longitude": 121.8081745560618
      },
      "timestamp": 1663903088299479007,
      "clipnumber": -1,
      "label": "ROAD_DRY",
      "clipname_video": "N/A",
      "state": "activated",
      "conditions": {
        "WeatherPrecipitation": [
          "PR_NO"
        ],
        "ConditionsLaneColor": [
          "LC_RED_GREEN_ORANGE"
        ],
        "ConditionsRoadCategory": [
          "RC_COUNTRY_ROADS"
        ],
        "ConditionsRoadStructure": [],
        "WeatherCloudiness": [
          "CL_PARTIALLY_CLOUDY"
        ],
        "ConditionsRoadState": [
          "ROAD_DRY"
        ],
        "ConditionsRoadType": [
          "RT_PAVED"
        ],
        "WeatherLight": [
          "LI_DAY"
        ]
      },
      "type": "multi-select",
      "frame_number": 32878
    },
    {
      "category": "Signs",
      "postion_coordinates": {
        "latitude": 25.107385142862917,
        "elevation": 80.96967315673828,
        "longitude": 121.80949957354443
      },
      "timestamp": 1663903174944036006,
      "clipnumber": -1,
      "label": "SIGN_PAVEMENT",
      "clipname_video": "N/A",
      "state": "",
      "conditions": {
        "WeatherPrecipitation": [
          "PR_NO"
        ],
        "ConditionsLaneColor": [
          "LC_RED_GREEN_ORANGE"
        ],
        "ConditionsRoadCategory": [
          "RC_COUNTRY_ROADS"
        ],
        "ConditionsRoadStructure": [],
        "WeatherCloudiness": [
          "CL_PARTIALLY_CLOUDY"
        ],
        "ConditionsRoadState": [
          "ROAD_DRY"
        ],
        "ConditionsRoadType": [
          "RT_PAVED"
        ],
        "WeatherLight": [
          "LI_DAY"
        ]
      },
      "type": "single",
      "frame_number": 35980
    },
    {
      "category": "OddObject",
      "postion_coordinates": {
        "latitude": 25.107397210830385,
        "elevation": 80.83761596679688,
        "longitude": 121.80952657825841
      },
      "timestamp": 1663903175469522953,
      "clipnumber": -1,
      "label": "OO_GENERAL_OBJ_HUMANS",
      "clipname_video": "N/A",
      "state": "",
      "conditions": {
        "WeatherPrecipitation": [
          "PR_NO"
        ],
        "ConditionsLaneColor": [
          "LC_RED_GREEN_ORANGE"
        ],
        "ConditionsRoadCategory": [
          "RC_COUNTRY_ROADS"
        ],
        "ConditionsRoadStructure": [],
        "WeatherCloudiness": [
          "CL_PARTIALLY_CLOUDY"
        ],
        "ConditionsRoadState": [
          "ROAD_DRY"
        ],
        "ConditionsRoadType": [
          "RT_PAVED"
        ],
        "WeatherLight": [
          "LI_DAY"
        ]
      },
      "type": "single",
      "frame_number": 36021
    },
    {
      "category": "Signs",
      "postion_coordinates": {
        "latitude": 25.107524989560826,
        "elevation": 80.08566284179688,
        "longitude": 121.809796905923
      },
      "timestamp": 1663903180469568967,
      "clipnumber": -1,
      "label": "SIGN_WARNING",
      "clipname_video": "N/A",
      "state": "",
      "conditions": {
        "WeatherPrecipitation": [
          "PR_NO"
        ],
        "ConditionsLaneColor": [
          "LC_RED_GREEN_ORANGE"
        ],
        "ConditionsRoadCategory": [
          "RC_COUNTRY_ROADS"
        ],
        "ConditionsRoadStructure": [],
        "WeatherCloudiness": [
          "CL_PARTIALLY_CLOUDY"
        ],
        "ConditionsRoadState": [
          "ROAD_DRY"
        ],
        "ConditionsRoadType": [
          "RT_PAVED"
        ],
        "WeatherLight": [
          "LI_DAY"
        ]
      },
      "type": "single",
      "frame_number": 36202
    },
    {
      "category": "Signs",
      "postion_coordinates": {
        "latitude": 25.1075344959733,
        "elevation": 80.04129791259766,
        "longitude": 121.80981711170143
      },
      "timestamp": 1663903180850999116,
      "clipnumber": -1,
      "label": "SIGN_SUPPLEMENTARY",
      "clipname_video": "N/A",
      "state": "",
      "conditions": {
        "WeatherPrecipitation": [
          "PR_NO"
        ],
        "ConditionsLaneColor": [
          "LC_RED_GREEN_ORANGE"
        ],
        "ConditionsRoadCategory": [
          "RC_COUNTRY_ROADS"
        ],
        "ConditionsRoadStructure": [],
        "WeatherCloudiness": [
          "CL_PARTIALLY_CLOUDY"
        ],
        "ConditionsRoadState": [
          "ROAD_DRY"
        ],
        "ConditionsRoadType": [
          "RT_PAVED"
        ],
        "WeatherLight": [
          "LI_DAY"
        ]
      },
      "type": "single",
      "frame_number": 36202
    },
    {
      "category": "OddObject",
      "postion_coordinates": {
        "latitude": 25.10755750733253,
        "elevation": 79.91217041015625,
        "longitude": 121.80986630990634
      },
      "timestamp": 1663903181950016975,
      "clipnumber": -1,
      "label": "OO_GENERAL_OBJ_HUMANS",
      "clipname_video": "N/A",
      "state": "",
      "conditions": {
        "WeatherPrecipitation": [
          "PR_NO"
        ],
        "ConditionsLaneColor": [
          "LC_RED_GREEN_ORANGE"
        ],
        "ConditionsRoadCategory": [
          "RC_COUNTRY_ROADS"
        ],
        "ConditionsRoadStructure": [],
        "WeatherCloudiness": [
          "CL_PARTIALLY_CLOUDY"
        ],
        "ConditionsRoadState": [
          "ROAD_DRY"
        ],
        "ConditionsRoadType": [
          "RT_PAVED"
        ],
        "WeatherLight": [
          "LI_DAY"
        ]
      },
      "type": "single",
      "frame_number": 36237
    },
    {
      "category": "ConditionsLaneColor",
      "postion_coordinates": {
        "latitude": 25.107748464793026,
        "elevation": 79.54798126220703,
        "longitude": 121.81033645233629
      },
      "timestamp": 1663903188991862058,
      "clipnumber": -1,
      "label": "LC_RED_GREEN_ORANGE",
      "clipname_video": "N/A",
      "state": "deactivated",
      "conditions": {
        "WeatherPrecipitation": [
          "PR_NO"
        ],
        "ConditionsLaneColor": [],
        "ConditionsRoadCategory": [
          "RC_COUNTRY_ROADS"
        ],
        "ConditionsRoadStructure": [],
        "WeatherCloudiness": [
          "CL_PARTIALLY_CLOUDY"
        ],
        "ConditionsRoadState": [
          "ROAD_DRY"
        ],
        "ConditionsRoadType": [
          "RT_PAVED"
        ],
        "WeatherLight": [
          "LI_DAY"
        ]
      },
      "type": "multi-select",
      "frame_number": 36487
    },
    {
      "category": "ConditionsLaneColor",
      "postion_coordinates": {
        "latitude": 25.107754934099297,
        "elevation": 79.53813171386719,
        "longitude": 121.8103622065471
      },
      "timestamp": 1663903189299597024,
      "clipnumber": -1,
      "label": "LC_YELLOW_BLUE",
      "clipname_video": "N/A",
      "state": "activated",
      "conditions": {
        "WeatherPrecipitation": [
          "PR_NO"
        ],
        "ConditionsLaneColor": [
          "LC_YELLOW_BLUE"
        ],
        "ConditionsRoadCategory": [
          "RC_COUNTRY_ROADS"
        ],
        "ConditionsRoadStructure": [],
        "WeatherCloudiness": [
          "CL_PARTIALLY_CLOUDY"
        ],
        "ConditionsRoadState": [
          "ROAD_DRY"
        ],
        "ConditionsRoadType": [
          "RT_PAVED"
        ],
        "WeatherLight": [
          "LI_DAY"
        ]
      },
      "type": "multi-select",
      "frame_number": 36523
    },
    {
      "category": "Signs",
      "postion_coordinates": {
        "latitude": 25.107837783386614,
        "elevation": 79.89115905761719,
        "longitude": 121.81081592850472
      },
      "timestamp": 1663903195149480104,
      "clipnumber": -1,
      "label": "SIGN_WARNING",
      "clipname_video": "N/A",
      "state": "",
      "conditions": {
        "WeatherPrecipitation": [
          "PR_NO"
        ],
        "ConditionsLaneColor": [
          "LC_YELLOW_BLUE"
        ],
        "ConditionsRoadCategory": [
          "RC_COUNTRY_ROADS"
        ],
        "ConditionsRoadStructure": [],
        "WeatherCloudiness": [
          "CL_PARTIALLY_CLOUDY"
        ],
        "ConditionsRoadState": [
          "ROAD_DRY"
        ],
        "ConditionsRoadType": [
          "RT_PAVED"
        ],
        "WeatherLight": [
          "LI_DAY"
        ]
      },
      "type": "single",
      "frame_number": 36744
    },
    {
      "category": "Signs",
      "postion_coordinates": {
        "latitude": 25.10784030527187,
        "elevation": 79.93980407714844,
        "longitude": 121.81083932588626
      },
      "timestamp": 1663903195499583959,
      "clipnumber": -1,
      "label": "SIGN_SUPPLEMENTARY",
      "clipname_video": "N/A",
      "state": "",
      "conditions": {
        "WeatherPrecipitation": [
          "PR_NO"
        ],
        "ConditionsLaneColor": [
          "LC_YELLOW_BLUE"
        ],
        "ConditionsRoadCategory": [
          "RC_COUNTRY_ROADS"
        ],
        "ConditionsRoadStructure": [],
        "WeatherCloudiness": [
          "CL_PARTIALLY_CLOUDY"
        ],
        "ConditionsRoadState": [
          "ROAD_DRY"
        ],
        "ConditionsRoadType": [
          "RT_PAVED"
        ],
        "WeatherLight": [
          "LI_DAY"
        ]
      },
      "type": "single",
      "frame_number": 36744
    },
    {
      "category": "Signs",
      "postion_coordinates": {
        "latitude": 25.107911393510427,
        "elevation": 80.5128173828125,
        "longitude": 121.8114477587474
      },
      "timestamp": 1663903204509608030,
      "clipnumber": -1,
      "label": "SIGN_PAVEMENT",
      "clipname_video": "N/A",
      "state": "",
      "conditions": {
        "WeatherPrecipitation": [
          "PR_NO"
        ],
        "ConditionsLaneColor": [
          "LC_YELLOW_BLUE"
        ],
        "ConditionsRoadCategory": [
          "RC_COUNTRY_ROADS"
        ],
        "ConditionsRoadStructure": [],
        "WeatherCloudiness": [
          "CL_PARTIALLY_CLOUDY"
        ],
        "ConditionsRoadState": [
          "ROAD_DRY"
        ],
        "ConditionsRoadType": [
          "RT_PAVED"
        ],
        "WeatherLight": [
          "LI_DAY"
        ]
      },
      "type": "single",
      "frame_number": 37062
    },
    {
      "category": "WeatherPrecipitation",
      "postion_coordinates": {
        "latitude": 25.10838858722407,
        "elevation": 82.1634521484375,
        "longitude": 121.81409924683423
      },
      "timestamp": 1663903252860707044,
      "clipnumber": -1,
      "label": "PR_NO",
      "clipname_video": "N/A",
      "state": "deactivated",
      "conditions": {},
      "type": "multi-select",
      "frame_number": 38693
    },
    {
      "category": "ConditionsLaneColor",
      "postion_coordinates": {
        "latitude": 25.10838858722407,
        "elevation": 82.1634521484375,
        "longitude": 121.81409924683423
      },
      "timestamp": 1663903252860707044,
      "clipnumber": -1,
      "label": "LC_YELLOW_BLUE",
      "clipname_video": "N/A",
      "state": "deactivated",
      "conditions": {},
      "type": "multi-select",
      "frame_number": 38693
    },
    {
      "category": "ConditionsRoadCategory",
      "postion_coordinates": {
        "latitude": 25.10838858722407,
        "elevation": 82.1634521484375,
        "longitude": 121.81409924683423
      },
      "timestamp": 1663903252860707044,
      "clipnumber": -1,
      "label": "RC_COUNTRY_ROADS",
      "clipname_video": "N/A",
      "state": "deactivated",
      "conditions": {},
      "type": "multi-select",
      "frame_number": 38693
    },
    {
      "category": "WeatherCloudiness",
      "postion_coordinates": {
        "latitude": 25.10838858722407,
        "elevation": 82.1634521484375,
        "longitude": 121.81409924683423
      },
      "timestamp": 1663903252860707044,
      "clipnumber": -1,
      "label": "CL_PARTIALLY_CLOUDY",
      "clipname_video": "N/A",
      "state": "deactivated",
      "conditions": {},
      "type": "multi-select",
      "frame_number": 38693
    },
    {
      "category": "ConditionsRoadState",
      "postion_coordinates": {
        "latitude": 25.10838858722407,
        "elevation": 82.1634521484375,
        "longitude": 121.81409924683423
      },
      "timestamp": 1663903252860707044,
      "clipnumber": -1,
      "label": "ROAD_DRY",
      "clipname_video": "N/A",
      "state": "deactivated",
      "conditions": {},
      "type": "multi-select",
      "frame_number": 38693
    },
    {
      "category": "ConditionsRoadState",
      "postion_coordinates": {
        "latitude": 25.10838858722407,
        "elevation": 82.1634521484375,
        "longitude": 121.81409924683423
      },
      "timestamp": 1663903252860707044,
      "clipnumber": -1,
      "label": "ROAD_DRY",
      "clipname_video": "N/A",
      "state": "deactivated",
      "conditions": {},
      "type": "multi-select",
      "frame_number": 38693
    },
    {
      "category": "ConditionsRoadType",
      "postion_coordinates": {
        "latitude": 25.10838858722407,
        "elevation": 82.1634521484375,
        "longitude": 121.81409924683423
      },
      "timestamp": 1663903252860707044,
      "clipnumber": -1,
      "label": "RT_PAVED",
      "clipname_video": "N/A",
      "state": "deactivated",
      "conditions": {},
      "type": "multi-select",
      "frame_number": 38693
    },
    {
      "category": "WeatherLight",
      "postion_coordinates": {
        "latitude": 25.10838858722407,
        "elevation": 82.1634521484375,
        "longitude": 121.81409924683423
      },
      "timestamp": 1663903252860707044,
      "clipnumber": -1,
      "label": "LI_DAY",
      "clipname_video": "N/A",
      "state": "deactivated",
      "conditions": {},
      "type": "multi-select",
      "frame_number": 38693
    }
  ]
}