{
  "metadata": {
    "comment": "",
    "campaign": "VALIDATION_DATA",
    "damage_events": "NO_EVENT",
    "driver_id": "2153",
    "driving_side": "RIGHT_DRIVING_SIDE",
    "steering_wheel_side": "LEFT_HAND_DRIVE",
    "camera_serial_number": "DCB3001",
    "vehicle_id": "WAUZZZF14KD025185",
    "extrinsic": {
      "__comment": "Global referencepoint is related to middle of rear axle",
      "antennas": {
        "antenna_left": {
          "origin": "[0.74333,0.42507,1.31982]",
          "yaw": "0",
          "roll": "0",
          "pitch": "0"
        },
        "antenna_right": {
          "origin": "[0.74286,-0.42698,1.31896]",
          "yaw": "0",
          "roll": "0",
          "pitch": "0"
        }
      },
      "cameras": {
        "camera_front_1": {
          "origin": "[1.94422,0.00107,1.17771]",
          "yaw": "0",
          "roll": "0",
          "pitch": "0"
        }
      },
      "imu": {
        "origin": "[0.428,-0.112,0.199]",
        "yaw": "0",
        "roll": "0",
        "pitch": "0"
      },
      "lidars": {
        "lidar_left": {
          "origin": "[1.74653,0.49440,1.34191]",
          "yaw": "0",
          "roll": "15",
          "pitch": "0"
        },
        "lidar_front": {
          "origin": "[1.810,0.0,1.343]",
          "yaw": "0",
          "roll": "0",
          "pitch": "0"
        },
        "lidar_right": {
          "origin": "[1.74653,-0.49440,1.34191]",
          "yaw": "0",
          "roll": "-15",
          "pitch": "0"
        }
      }
    },
    "governance": {
      "location": "Ingolstadt",
      "pool": "audi_mfk5_camera"
    },
    "rear_axle_steering": "YES",
    "logger_sw_version": "5.01.F070",
    "logger": "X2E",
    "ros_visualization_version": "5.2.0",
    "meta_data_version": "1.2.0",
    "vehicle_number_plate": "AB-ME 7800",
    "group_project_name": "MFK5",
    "vehicle_region": "EUROPE_EU",
    "brand": "AUDI",
    "tire_type": "SUMMER_TIRE",
    "windshield_number_front": "2",
    "vehicle_load_change": "PASSENGER_HOP_ON",
    "group_vehicle_number": "AU416000000",
    "workshop_events": "NO_EVENT",
    "windshield_type_front": "INSULATING_GLASS_HUD",
    "country": "MX",
    "region": "AMERICA",
    "test_track_id": "mfk5",
    "windshield_serial_number_front": "4M8 845 099",
    "vehicle_platform": "PPE",
    "time": {
      "timestamp": 1644448072777909040,
      "domain": "UTC",
      "confidence_class": "AUTO_RETRIEVAL"
    },
    "suspension_system": "AIR",
    "position": {
      "source": "GPS",
      "domain": "WGS84",
      "confidence_class": "AUTO_RETRIEVAL"
    },
    "model": "Q8",
    "us_state": "",
    "headlight_type": "MATRIX",
    "CarryoverFromMFK5": true
  },
  "prelabels": [
    {
      "category": "WeatherCloudiness",
      "postion_coordinates": {
        "latitude": 19.421641229510843,
        "elevation": 2355.085205078125,
        "longitude": -97.63632367108181
      },
      "timestamp": 1644448112721031904,
      "clipnumber": -1,
      "label": "CL_PARTIALLY_CLOUDY",
      "clipname_video": "N/A",
      "state": "activated",
      "conditions": {
        "WeatherCloudiness": [
          "CL_PARTIALLY_CLOUDY"
        ]
      },
      "type": "multi-select",
      "frame_number": 8545
    },
    {
      "category": "WeatherPrecipitation",
      "postion_coordinates": {
        "latitude": 19.421724122341892,
        "elevation": 2355.26416015625,
        "longitude": -97.63621536262208
      },
      "timestamp": 1644448113438235998,
      "clipnumber": -1,
      "label": "PR_NO",
      "clipname_video": "N/A",
      "state": "activated",
      "conditions": {
        "WeatherPrecipitation": [
          "PR_NO"
        ],
        "WeatherCloudiness": [
          "CL_PARTIALLY_CLOUDY"
        ]
      },
      "type": "multi-select",
      "frame_number": 8586
    },
    {
      "category": "WeatherLight",
      "postion_coordinates": {
        "latitude": 19.422528420491638,
        "elevation": 2357.19091796875,
        "longitude": -97.6351569218661
      },
      "timestamp": 1644448119459305047,
      "clipnumber": -1,
      "label": "LI_DAY",
      "clipname_video": "N/A",
      "state": "activated",
      "conditions": {
        "WeatherPrecipitation": [
          "PR_NO"
        ],
        "WeatherCloudiness": [
          "CL_PARTIALLY_CLOUDY"
        ],
        "WeatherLight": [
          "LI_DAY"
        ]
      },
      "type": "multi-select",
      "frame_number": 8805
    },
    {
      "category": "ConditionsRoadCategory",
      "postion_coordinates": {
        "latitude": 19.423319008649933,
        "elevation": 2357.01171875,
        "longitude": -97.63411414291585
      },
      "timestamp": 1644448125877931118,
      "clipnumber": -1,
      "label": "RC_HIGHWAY",
      "clipname_video": "N/A",
      "state": "activated",
      "conditions": {
        "WeatherPrecipitation": [
          "PR_NO"
        ],
        "WeatherCloudiness": [
          "CL_PARTIALLY_CLOUDY"
        ],
        "ConditionsRoadCategory": [
          "RC_HIGHWAY"
        ],
        "WeatherLight": [
          "LI_DAY"
        ]
      },
      "type": "multi-select",
      "frame_number": 9057
    },
    {
      "category": "WeatherSightInterference",
      "postion_coordinates": {
        "latitude": 19.423456063218662,
        "elevation": 2356.779296875,
        "longitude": -97.6339335190172
      },
      "timestamp": 1644448127087861061,
      "clipnumber": -1,
      "label": "SI_LOW_SUN_BEHIND",
      "clipname_video": "N/A",
      "state": "activated",
      "conditions": {
        "WeatherPrecipitation": [
          "PR_NO"
        ],
        "WeatherSightInterference": [
          "SI_LOW_SUN_BEHIND"
        ],
        "WeatherCloudiness": [
          "CL_PARTIALLY_CLOUDY"
        ],
        "ConditionsRoadCategory": [
          "RC_HIGHWAY"
        ],
        "WeatherLight": [
          "LI_DAY"
        ]
      },
      "type": "multi-select",
      "frame_number": 9091
    },
    {
      "category": "ConditionsRoadType",
      "postion_coordinates": {
        "latitude": 19.42449314219684,
        "elevation": 2353.377685546875,
        "longitude": -97.63256308033235
      },
      "timestamp": 1644448135568175077,
      "clipnumber": -1,
      "label": "RT_PAVED",
      "clipname_video": "N/A",
      "state": "activated",
      "conditions": {
        "WeatherPrecipitation": [
          "PR_NO"
        ],
        "ConditionsRoadCategory": [
          "RC_HIGHWAY"
        ],
        "WeatherCloudiness": [
          "CL_PARTIALLY_CLOUDY"
        ],
        "ConditionsRoadType": [
          "RT_PAVED"
        ],
        "WeatherLight": [
          "LI_DAY"
        ],
        "WeatherSightInterference": [
          "SI_LOW_SUN_BEHIND"
        ]
      },
      "type": "multi-select",
      "frame_number": 9374
    },
    {
      "category": "ConditionsRoadState",
      "postion_coordinates": {
        "latitude": 19.425460508701956,
        "elevation": 2350.2646484375,
        "longitude": -97.63128887975192
      },
      "timestamp": 1644448143027946949,
      "clipnumber": -1,
      "label": "ROAD_DRY",
      "clipname_video": "N/A",
      "state": "activated",
      "conditions": {
        "WeatherPrecipitation": [
          "PR_NO"
        ],
        "ConditionsRoadCategory": [
          "RC_HIGHWAY"
        ],
        "WeatherCloudiness": [
          "CL_PARTIALLY_CLOUDY"
        ],
        "ConditionsRoadState": [
          "ROAD_DRY"
        ],
        "ConditionsRoadType": [
          "RT_PAVED"
        ],
        "WeatherLight": [
          "LI_DAY"
        ],
        "WeatherSightInterference": [
          "SI_LOW_SUN_BEHIND"
        ]
      },
      "type": "multi-select",
      "frame_number": 9664
    },
    {
      "category": "Signs",
      "postion_coordinates": {
        "latitude": 19.426285281386157,
        "elevation": 2347.936767578125,
        "longitude": -97.63019921499951
      },
      "timestamp": 1644448148957861900,
      "clipnumber": -1,
      "label": "SIGN_NO_PASSING",
      "clipname_video": "N/A",
      "state": "",
      "conditions": {
        "WeatherPrecipitation": [
          "PR_NO"
        ],
        "ConditionsRoadCategory": [
          "RC_HIGHWAY"
        ],
        "WeatherCloudiness": [
          "CL_PARTIALLY_CLOUDY"
        ],
        "ConditionsRoadState": [
          "ROAD_DRY"
        ],
        "ConditionsRoadType": [
          "RT_PAVED"
        ],
        "WeatherLight": [
          "LI_DAY"
        ],
        "WeatherSightInterference": [
          "SI_LOW_SUN_BEHIND"
        ]
      },
      "type": "single",
      "frame_number": 9884
    },
    {
      "category": "ConditionsRoadEdge",
      "postion_coordinates": {
        "latitude": 19.426686445052155,
        "elevation": 2347.354736328125,
        "longitude": -97.62965909231536
      },
      "timestamp": 1644448152027869939,
      "clipnumber": -1,
      "label": "RE_CURB",
      "clipname_video": "N/A",
      "state": "",
      "conditions": {
        "WeatherPrecipitation": [
          "PR_NO"
        ],
        "ConditionsRoadCategory": [
          "RC_HIGHWAY"
        ],
        "WeatherCloudiness": [
          "CL_PARTIALLY_CLOUDY"
        ],
        "ConditionsRoadState": [
          "ROAD_DRY"
        ],
        "ConditionsRoadType": [
          "RT_PAVED"
        ],
        "WeatherLight": [
          "LI_DAY"
        ],
        "WeatherSightInterference": [
          "SI_LOW_SUN_BEHIND"
        ]
      },
      "type": "single",
      "frame_number": 9988
    },
    {
      "category": "ConditionsLaneColor",
      "postion_coordinates": {
        "latitude": 19.427247827145816,
        "elevation": 2346.872314453125,
        "longitude": -97.62891610130715
      },
      "timestamp": 1644448156067861080,
      "clipnumber": -1,
      "label": "LC_YELLOW_BLUE",
      "clipname_video": "N/A",
      "state": "activated",
      "conditions": {
        "WeatherPrecipitation": [
          "PR_NO"
        ],
        "ConditionsLaneColor": [
          "LC_YELLOW_BLUE"
        ],
        "ConditionsRoadCategory": [
          "RC_HIGHWAY"
        ],
        "WeatherCloudiness": [
          "CL_PARTIALLY_CLOUDY"
        ],
        "ConditionsRoadState": [
          "ROAD_DRY"
        ],
        "ConditionsRoadType": [
          "RT_PAVED"
        ],
        "WeatherLight": [
          "LI_DAY"
        ],
        "WeatherSightInterference": [
          "SI_LOW_SUN_BEHIND"
        ]
      },
      "type": "multi-select",
      "frame_number": 10133
    },
    {
      "category": "ConditionsRoadEdge",
      "postion_coordinates": {
        "latitude": 19.427550331592027,
        "elevation": 2346.656005859375,
        "longitude": -97.62852122969366
      },
      "timestamp": 1644448158227902889,
      "clipnumber": -1,
      "label": "RE_GUARD_RAIL",
      "clipname_video": "N/A",
      "state": "",
      "conditions": {
        "WeatherPrecipitation": [
          "PR_NO"
        ],
        "ConditionsLaneColor": [
          "LC_YELLOW_BLUE"
        ],
        "ConditionsRoadCategory": [
          "RC_HIGHWAY"
        ],
        "WeatherCloudiness": [
          "CL_PARTIALLY_CLOUDY"
        ],
        "ConditionsRoadState": [
          "ROAD_DRY"
        ],
        "ConditionsRoadType": [
          "RT_PAVED"
        ],
        "WeatherLight": [
          "LI_DAY"
        ],
        "WeatherSightInterference": [
          "SI_LOW_SUN_BEHIND"
        ]
      },
      "type": "single",
      "frame_number": 10208
    },
    {
      "category": "Signs",
      "postion_coordinates": {
        "latitude": 19.427918539862105,
        "elevation": 2346.310546875,
        "longitude": -97.62803344470889
      },
      "timestamp": 1644448160877863883,
      "clipnumber": -1,
      "label": "SIGN_SPEED_LIMIT_IMPLICIT",
      "clipname_video": "N/A",
      "state": "",
      "conditions": {
        "WeatherPrecipitation": [
          "PR_NO"
        ],
        "ConditionsLaneColor": [
          "LC_YELLOW_BLUE"
        ],
        "ConditionsRoadCategory": [
          "RC_HIGHWAY"
        ],
        "WeatherCloudiness": [
          "CL_PARTIALLY_CLOUDY"
        ],
        "ConditionsRoadState": [
          "ROAD_DRY"
        ],
        "ConditionsRoadType": [
          "RT_PAVED"
        ],
        "WeatherLight": [
          "LI_DAY"
        ],
        "WeatherSightInterference": [
          "SI_LOW_SUN_BEHIND"
        ]
      },
      "type": "single",
      "frame_number": 10315
    },
    {
      "category": "ConditionsRoadEdge",
      "postion_coordinates": {
        "latitude": 19.43052137791289,
        "elevation": 2345.69384765625,
        "longitude": -97.62456588168618
      },
      "timestamp": 1644448180957879066,
      "clipnumber": -1,
      "label": "RE_GUARD_RAIL",
      "clipname_video": "N/A",
      "state": "",
      "conditions": {
        "WeatherPrecipitation": [
          "PR_NO"
        ],
        "ConditionsLaneColor": [
          "LC_YELLOW_BLUE"
        ],
        "ConditionsRoadCategory": [
          "RC_HIGHWAY"
        ],
        "WeatherCloudiness": [
          "CL_PARTIALLY_CLOUDY"
        ],
        "ConditionsRoadState": [
          "ROAD_DRY"
        ],
        "ConditionsRoadType": [
          "RT_PAVED"
        ],
        "WeatherLight": [
          "LI_DAY"
        ],
        "WeatherSightInterference": [
          "SI_LOW_SUN_BEHIND"
        ]
      },
      "type": "single",
      "frame_number": 11038
    },
    {
      "category": "ConditionsRoadEdge",
      "postion_coordinates": {
        "latitude": 19.43149673157069,
        "elevation": 2344.669189453125,
        "longitude": -97.62317300960358
      },
      "timestamp": 1644448189127945899,
      "clipnumber": -1,
      "label": "RE_GUARD_RAIL",
      "clipname_video": "N/A",
      "state": "",
      "conditions": {
        "WeatherPrecipitation": [
          "PR_NO"
        ],
        "ConditionsLaneColor": [
          "LC_YELLOW_BLUE"
        ],
        "ConditionsRoadCategory": [
          "RC_HIGHWAY"
        ],
        "WeatherCloudiness": [
          "CL_PARTIALLY_CLOUDY"
        ],
        "ConditionsRoadState": [
          "ROAD_DRY"
        ],
        "ConditionsRoadType": [
          "RT_PAVED"
        ],
        "WeatherLight": [
          "LI_DAY"
        ],
        "WeatherSightInterference": [
          "SI_LOW_SUN_BEHIND"
        ]
      },
      "type": "single",
      "frame_number": 11322
    },
    {
      "category": "ConditionsRoadStructure",
      "postion_coordinates": {
        "latitude": 19.434329476054465,
        "elevation": 2342.542724609375,
        "longitude": -97.61887706205809
      },
      "timestamp": 1644448214478784084,
      "clipnumber": -1,
      "label": "RS_UNDERPASS",
      "clipname_video": "N/A",
      "state": "activated",
      "conditions": {
        "WeatherPrecipitation": [
          "PR_NO"
        ],
        "ConditionsLaneColor": [
          "LC_YELLOW_BLUE"
        ],
        "ConditionsRoadCategory": [
          "RC_HIGHWAY"
        ],
        "ConditionsRoadStructure": [
          "RS_UNDERPASS"
        ],
        "WeatherCloudiness": [
          "CL_PARTIALLY_CLOUDY"
        ],
        "ConditionsRoadState": [
          "ROAD_DRY"
        ],
        "ConditionsRoadType": [
          "RT_PAVED"
        ],
        "WeatherLight": [
          "LI_DAY"
        ],
        "WeatherSightInterference": [
          "SI_LOW_SUN_BEHIND"
        ]
      },
      "type": "multi-select",
      "frame_number": 12226
    },
    {
      "category": "ConditionsRoadStructure",
      "postion_coordinates": {
        "latitude": 19.43492331638777,
        "elevation": 2342.4072265625,
        "longitude": -97.61796914398671
      },
      "timestamp": 1644448219650758028,
      "clipnumber": -1,
      "label": "RS_UNDERPASS",
      "clipname_video": "N/A",
      "state": "deactivated",
      "conditions": {
        "WeatherPrecipitation": [
          "PR_NO"
        ],
        "ConditionsLaneColor": [
          "LC_YELLOW_BLUE"
        ],
        "ConditionsRoadCategory": [
          "RC_HIGHWAY"
        ],
        "ConditionsRoadStructure": [],
        "WeatherCloudiness": [
          "CL_PARTIALLY_CLOUDY"
        ],
        "ConditionsRoadState": [
          "ROAD_DRY"
        ],
        "ConditionsRoadType": [
          "RT_PAVED"
        ],
        "WeatherLight": [
          "LI_DAY"
        ],
        "WeatherSightInterference": [
          "SI_LOW_SUN_BEHIND"
        ]
      },
      "type": "multi-select",
      "frame_number": 12404
    },
    {
      "category": "ConditionsRoadEdge",
      "postion_coordinates": {
        "latitude": 19.435567203282687,
        "elevation": 2343.13623046875,
        "longitude": -97.61699190353
      },
      "timestamp": 1644448225598393917,
      "clipnumber": -1,
      "label": "RE_WITHOUT_PAINTED_LINES",
      "clipname_video": "N/A",
      "state": "",
      "conditions": {
        "WeatherPrecipitation": [
          "PR_NO"
        ],
        "ConditionsLaneColor": [
          "LC_YELLOW_BLUE"
        ],
        "ConditionsRoadCategory": [
          "RC_HIGHWAY"
        ],
        "ConditionsRoadStructure": [],
        "WeatherCloudiness": [
          "CL_PARTIALLY_CLOUDY"
        ],
        "ConditionsRoadState": [
          "ROAD_DRY"
        ],
        "ConditionsRoadType": [
          "RT_PAVED"
        ],
        "WeatherLight": [
          "LI_DAY"
        ],
        "WeatherSightInterference": [
          "SI_LOW_SUN_BEHIND"
        ]
      },
      "type": "single",
      "frame_number": 12618
    },
    {
      "category": "Signs",
      "postion_coordinates": {
        "latitude": 19.435688245415765,
        "elevation": 2343.2958984375,
        "longitude": -97.61680857204539
      },
      "timestamp": 1644448226709654092,
      "clipnumber": -1,
      "label": "SIGN_NO_PASSING",
      "clipname_video": "N/A",
      "state": "",
      "conditions": {
        "WeatherPrecipitation": [
          "PR_NO"
        ],
        "ConditionsLaneColor": [
          "LC_YELLOW_BLUE"
        ],
        "ConditionsRoadCategory": [
          "RC_HIGHWAY"
        ],
        "ConditionsRoadStructure": [],
        "WeatherCloudiness": [
          "CL_PARTIALLY_CLOUDY"
        ],
        "ConditionsRoadState": [
          "ROAD_DRY"
        ],
        "ConditionsRoadType": [
          "RT_PAVED"
        ],
        "WeatherLight": [
          "LI_DAY"
        ],
        "WeatherSightInterference": [
          "SI_LOW_SUN_BEHIND"
        ]
      },
      "type": "single",
      "frame_number": 12653
    },
    {
      "category": "ConditionsRoadEdge",
      "postion_coordinates": {
        "latitude": 19.43949847937929,
        "elevation": 2340.958251953125,
        "longitude": -97.6110138326056
      },
      "timestamp": 1644448261891963005,
      "clipnumber": -1,
      "label": "RE_CURB",
      "clipname_video": "N/A",
      "state": "",
      "conditions": {
        "WeatherPrecipitation": [
          "PR_NO"
        ],
        "ConditionsLaneColor": [
          "LC_YELLOW_BLUE"
        ],
        "ConditionsRoadCategory": [
          "RC_HIGHWAY"
        ],
        "ConditionsRoadStructure": [],
        "WeatherCloudiness": [
          "CL_PARTIALLY_CLOUDY"
        ],
        "ConditionsRoadState": [
          "ROAD_DRY"
        ],
        "ConditionsRoadType": [
          "RT_PAVED"
        ],
        "WeatherLight": [
          "LI_DAY"
        ],
        "WeatherSightInterference": [
          "SI_LOW_SUN_BEHIND"
        ]
      },
      "type": "single",
      "frame_number": 13952
    },
    {
      "category": "ConditionsRoadStructure",
      "postion_coordinates": {
        "latitude": 19.44027265490897,
        "elevation": 2342.211669921875,
        "longitude": -97.60983930115957
      },
      "timestamp": 1644448268652792930,
      "clipnumber": -1,
      "label": "RS_BRIDGE",
      "clipname_video": "N/A",
      "state": "activated",
      "conditions": {
        "WeatherPrecipitation": [
          "PR_NO"
        ],
        "ConditionsLaneColor": [
          "LC_YELLOW_BLUE"
        ],
        "ConditionsRoadCategory": [
          "RC_HIGHWAY"
        ],
        "ConditionsRoadStructure": [
          "RS_BRIDGE"
        ],
        "WeatherCloudiness": [
          "CL_PARTIALLY_CLOUDY"
        ],
        "ConditionsRoadState": [
          "ROAD_DRY"
        ],
        "ConditionsRoadType": [
          "RT_PAVED"
        ],
        "WeatherLight": [
          "LI_DAY"
        ],
        "WeatherSightInterference": [
          "SI_LOW_SUN_BEHIND"
        ]
      },
      "type": "multi-select",
      "frame_number": 14170
    },
    {
      "category": "ConditionsRoadEdge",
      "postion_coordinates": {
        "latitude": 19.440606954567972,
        "elevation": 2342.9013671875,
        "longitude": -97.60933416171328
      },
      "timestamp": 1644448271801989078,
      "clipnumber": -1,
      "label": "RE_GUARD_RAIL",
      "clipname_video": "N/A",
      "state": "",
      "conditions": {
        "WeatherPrecipitation": [
          "PR_NO"
        ],
        "ConditionsLaneColor": [
          "LC_YELLOW_BLUE"
        ],
        "ConditionsRoadCategory": [
          "RC_HIGHWAY"
        ],
        "ConditionsRoadStructure": [
          "RS_BRIDGE"
        ],
        "WeatherCloudiness": [
          "CL_PARTIALLY_CLOUDY"
        ],
        "ConditionsRoadState": [
          "ROAD_DRY"
        ],
        "ConditionsRoadType": [
          "RT_PAVED"
        ],
        "WeatherLight": [
          "LI_DAY"
        ],
        "WeatherSightInterference": [
          "SI_LOW_SUN_BEHIND"
        ]
      },
      "type": "single",
      "frame_number": 14276
    },
    {
      "category": "ConditionsRoadStructure",
      "postion_coordinates": {
        "latitude": 19.441541713664055,
        "elevation": 2342.89013671875,
        "longitude": -97.60790695182054
      },
      "timestamp": 1644448280051868915,
      "clipnumber": -1,
      "label": "RS_BRIDGE",
      "clipname_video": "N/A",
      "state": "deactivated",
      "conditions": {
        "WeatherPrecipitation": [
          "PR_NO"
        ],
        "ConditionsLaneColor": [
          "LC_YELLOW_BLUE"
        ],
        "ConditionsRoadCategory": [
          "RC_HIGHWAY"
        ],
        "ConditionsRoadStructure": [],
        "WeatherCloudiness": [
          "CL_PARTIALLY_CLOUDY"
        ],
        "ConditionsRoadState": [
          "ROAD_DRY"
        ],
        "ConditionsRoadType": [
          "RT_PAVED"
        ],
        "WeatherLight": [
          "LI_DAY"
        ],
        "WeatherSightInterference": [
          "SI_LOW_SUN_BEHIND"
        ]
      },
      "type": "multi-select",
      "frame_number": 14598
    },
    {
      "category": "Signs",
      "postion_coordinates": {
        "latitude": 19.44408196738096,
        "elevation": 2341.259033203125,
        "longitude": -97.6040438745573
      },
      "timestamp": 1644448302862008094,
      "clipnumber": -1,
      "label": "SIGN_SPEED_LIMIT_IMPLICIT",
      "clipname_video": "N/A",
      "state": "",
      "conditions": {
        "WeatherPrecipitation": [
          "PR_NO"
        ],
        "ConditionsLaneColor": [
          "LC_YELLOW_BLUE"
        ],
        "ConditionsRoadCategory": [
          "RC_HIGHWAY"
        ],
        "ConditionsRoadStructure": [],
        "WeatherCloudiness": [
          "CL_PARTIALLY_CLOUDY"
        ],
        "ConditionsRoadState": [
          "ROAD_DRY"
        ],
        "ConditionsRoadType": [
          "RT_PAVED"
        ],
        "WeatherLight": [
          "LI_DAY"
        ],
        "WeatherSightInterference": [
          "SI_LOW_SUN_BEHIND"
        ]
      },
      "type": "single",
      "frame_number": 15422
    },
    {
      "category": "ConditionsRoadEdge",
      "postion_coordinates": {
        "latitude": 19.44575884994469,
        "elevation": 2341.757568359375,
        "longitude": -97.60149690009409
      },
      "timestamp": 1644448317302191019,
      "clipnumber": -1,
      "label": "RE_GUARD_RAIL",
      "clipname_video": "N/A",
      "state": "",
      "conditions": {
        "WeatherPrecipitation": [
          "PR_NO"
        ],
        "ConditionsLaneColor": [
          "LC_YELLOW_BLUE"
        ],
        "ConditionsRoadCategory": [
          "RC_HIGHWAY"
        ],
        "ConditionsRoadStructure": [],
        "WeatherCloudiness": [
          "CL_PARTIALLY_CLOUDY"
        ],
        "ConditionsRoadState": [
          "ROAD_DRY"
        ],
        "ConditionsRoadType": [
          "RT_PAVED"
        ],
        "WeatherLight": [
          "LI_DAY"
        ],
        "WeatherSightInterference": [
          "SI_LOW_SUN_BEHIND"
        ]
      },
      "type": "single",
      "frame_number": 15930
    },
    {
      "category": "ConditionsRoadEdge",
      "postion_coordinates": {
        "latitude": 19.446103965994432,
        "elevation": 2341.662841796875,
        "longitude": -97.6009819681782
      },
      "timestamp": 1644448320271919965,
      "clipnumber": -1,
      "label": "RE_WITHOUT_PAINTED_LINES",
      "clipname_video": "N/A",
      "state": "",
      "conditions": {
        "WeatherPrecipitation": [
          "PR_NO"
        ],
        "ConditionsLaneColor": [
          "LC_YELLOW_BLUE"
        ],
        "ConditionsRoadCategory": [
          "RC_HIGHWAY"
        ],
        "ConditionsRoadStructure": [],
        "WeatherCloudiness": [
          "CL_PARTIALLY_CLOUDY"
        ],
        "ConditionsRoadState": [
          "ROAD_DRY"
        ],
        "ConditionsRoadType": [
          "RT_PAVED"
        ],
        "WeatherLight": [
          "LI_DAY"
        ],
        "WeatherSightInterference": [
          "SI_LOW_SUN_BEHIND"
        ]
      },
      "type": "single",
      "frame_number": 16038
    },
    {
      "category": "Signs",
      "postion_coordinates": {
        "latitude": 19.44668457672308,
        "elevation": 2341.47216796875,
        "longitude": -97.60013279236541
      },
      "timestamp": 1644448325322082996,
      "clipnumber": -1,
      "label": "SIGN_EMBEDDED",
      "clipname_video": "N/A",
      "state": "",
      "conditions": {
        "WeatherPrecipitation": [
          "PR_NO"
        ],
        "ConditionsLaneColor": [
          "LC_YELLOW_BLUE"
        ],
        "ConditionsRoadCategory": [
          "RC_HIGHWAY"
        ],
        "ConditionsRoadStructure": [],
        "WeatherCloudiness": [
          "CL_PARTIALLY_CLOUDY"
        ],
        "ConditionsRoadState": [
          "ROAD_DRY"
        ],
        "ConditionsRoadType": [
          "RT_PAVED"
        ],
        "WeatherLight": [
          "LI_DAY"
        ],
        "WeatherSightInterference": [
          "SI_LOW_SUN_BEHIND"
        ]
      },
      "type": "single",
      "frame_number": 16218
    },
    {
      "category": "WeatherPrecipitation",
      "postion_coordinates": {
        "latitude": 19.44960667022545,
        "elevation": 2338.689208984375,
        "longitude": -97.59608465627538
      },
      "timestamp": 1644448351201900005,
      "clipnumber": -1,
      "label": "PR_NO",
      "clipname_video": "N/A",
      "state": "deactivated",
      "conditions": {},
      "type": "multi-select",
      "frame_number": 17158
    },
    {
      "category": "ConditionsLaneColor",
      "postion_coordinates": {
        "latitude": 19.44960667022545,
        "elevation": 2338.689208984375,
        "longitude": -97.59608465627538
      },
      "timestamp": 1644448351201900005,
      "clipnumber": -1,
      "label": "LC_YELLOW_BLUE",
      "clipname_video": "N/A",
      "state": "deactivated",
      "conditions": {},
      "type": "multi-select",
      "frame_number": 17158
    },
    {
      "category": "ConditionsRoadCategory",
      "postion_coordinates": {
        "latitude": 19.44960667022545,
        "elevation": 2338.689208984375,
        "longitude": -97.59608465627538
      },
      "timestamp": 1644448351201900005,
      "clipnumber": -1,
      "label": "RC_HIGHWAY",
      "clipname_video": "N/A",
      "state": "deactivated",
      "conditions": {},
      "type": "multi-select",
      "frame_number": 17158
    },
    {
      "category": "WeatherCloudiness",
      "postion_coordinates": {
        "latitude": 19.44960667022545,
        "elevation": 2338.689208984375,
        "longitude": -97.59608465627538
      },
      "timestamp": 1644448351201900005,
      "clipnumber": -1,
      "label": "CL_PARTIALLY_CLOUDY",
      "clipname_video": "N/A",
      "state": "deactivated",
      "conditions": {},
      "type": "multi-select",
      "frame_number": 17158
    },
    {
      "category": "ConditionsRoadState",
      "postion_coordinates": {
        "latitude": 19.44960667022545,
        "elevation": 2338.689208984375,
        "longitude": -97.59608465627538
      },
      "timestamp": 1644448351201900005,
      "clipnumber": -1,
      "label": "ROAD_DRY",
      "clipname_video": "N/A",
      "state": "deactivated",
      "conditions": {},
      "type": "multi-select",
      "frame_number": 17158
    },
    {
      "category": "ConditionsRoadType",
      "postion_coordinates": {
        "latitude": 19.44960667022545,
        "elevation": 2338.689208984375,
        "longitude": -97.59608465627538
      },
      "timestamp": 1644448351201900005,
      "clipnumber": -1,
      "label": "RT_PAVED",
      "clipname_video": "N/A",
      "state": "deactivated",
      "conditions": {},
      "type": "multi-select",
      "frame_number": 17158
    },
    {
      "category": "WeatherLight",
      "postion_coordinates": {
        "latitude": 19.44960667022545,
        "elevation": 2338.689208984375,
        "longitude": -97.59608465627538
      },
      "timestamp": 1644448351201900005,
      "clipnumber": -1,
      "label": "LI_DAY",
      "clipname_video": "N/A",
      "state": "deactivated",
      "conditions": {},
      "type": "multi-select",
      "frame_number": 17158
    },
    {
      "category": "WeatherSightInterference",
      "postion_coordinates": {
        "latitude": 19.44960667022545,
        "elevation": 2338.689208984375,
        "longitude": -97.59608465627538
      },
      "timestamp": 1644448351201900005,
      "clipnumber": -1,
      "label": "SI_LOW_SUN_BEHIND",
      "clipname_video": "N/A",
      "state": "deactivated",
      "conditions": {},
      "type": "multi-select",
      "frame_number": 17158
    }
  ]
}