{
  "metadata": {
    "comment": "",
    "campaign": "VALIDATION_DATA",
    "damage_events": "NO_EVENT",
    "driver_id": "2153",
    "driving_side": "RIGHT_DRIVING_SIDE",
    "steering_wheel_side": "LEFT_HAND_DRIVE",
    "camera_serial_number": "DCB3001",
    "vehicle_id": "WAUZZZF14KD025185",
    "extrinsic": {
      "__comment": "Global referencepoint is related to middle of rear axle",
      "antennas": {
        "antenna_left": {
          "origin": "[0.74333,0.42507,1.31982]",
          "yaw": "0",
          "roll": "0",
          "pitch": "0"
        },
        "antenna_right": {
          "origin": "[0.74286,-0.42698,1.31896]",
          "yaw": "0",
          "roll": "0",
          "pitch": "0"
        }
      },
      "cameras": {
        "camera_front_1": {
          "origin": "[1.94422,0.00107,1.17771]",
          "yaw": "0",
          "roll": "0",
          "pitch": "0"
        }
      },
      "imu": {
        "origin": "[0.428,-0.112,0.199]",
        "yaw": "0",
        "roll": "0",
        "pitch": "0"
      },
      "lidars": {
        "lidar_left": {
          "origin": "[1.74653,0.49440,1.34191]",
          "yaw": "0",
          "roll": "15",
          "pitch": "0"
        },
        "lidar_front": {
          "origin": "[1.810,0.0,1.343]",
          "yaw": "0",
          "roll": "0",
          "pitch": "0"
        },
        "lidar_right": {
          "origin": "[1.74653,-0.49440,1.34191]",
          "yaw": "0",
          "roll": "-15",
          "pitch": "0"
        }
      }
    },
    "governance": {
      "location": "Ingolstadt",
      "pool": "audi_mfk5_camera"
    },
    "rear_axle_steering": "YES",
    "logger_sw_version": "5.01.F070",
    "logger": "X2E",
    "ros_visualization_version": "5.2.0",
    "meta_data_version": "1.2.0",
    "vehicle_number_plate": "AB-ME 7800",
    "group_project_name": "MFK5",
    "vehicle_region": "EUROPE_EU",
    "brand": "AUDI",
    "tire_type": "SUMMER_TIRE",
    "windshield_number_front": "2",
    "vehicle_load_change": "PASSENGER_HOP_ON",
    "group_vehicle_number": "AU416000000",
    "workshop_events": "NO_EVENT",
    "windshield_type_front": "INSULATING_GLASS_HUD",
    "country": "MX",
    "region": "AMERICA",
    "test_track_id": "mfk5",
    "windshield_serial_number_front": "4M8 845 099",
    "vehicle_platform": "PPE",
    "time": {
      "timestamp": 1644447433278641939,
      "domain": "UTC",
      "confidence_class": "AUTO_RETRIEVAL"
    },
    "suspension_system": "AIR",
    "position": {
      "source": "GPS",
      "domain": "WGS84",
      "confidence_class": "AUTO_RETRIEVAL"
    },
    "model": "Q8",
    "us_state": "",
    "headlight_type": "MATRIX",
    "CarryoverFromMFK5": true
  },
  "prelabels": [
    {
      "category": "WeatherCloudiness",
      "postion_coordinates": {
        "latitude": 19.37740283935479,
        "elevation": 2479.32470703125,
        "longitude": -97.7109203967116
      },
      "timestamp": 1644447515028927087,
      "clipnumber": -1,
      "label": "CL_PARTIALLY_CLOUDY",
      "clipname_video": "N/A",
      "state": "activated",
      "conditions": {
        "WeatherCloudiness": [
          "CL_PARTIALLY_CLOUDY"
        ]
      },
      "type": "multi-select",
      "frame_number": 6100
    },
    {
      "category": "WeatherPrecipitation",
      "postion_coordinates": {
        "latitude": 19.377449638376707,
        "elevation": 2480.39208984375,
        "longitude": -97.71076551946746
      },
      "timestamp": 1644447517698719024,
      "clipnumber": -1,
      "label": "PR_NO",
      "clipname_video": "N/A",
      "state": "activated",
      "conditions": {
        "WeatherPrecipitation": [
          "PR_NO"
        ],
        "WeatherCloudiness": [
          "CL_PARTIALLY_CLOUDY"
        ]
      },
      "type": "multi-select",
      "frame_number": 6210
    },
    {
      "category": "WeatherLight",
      "postion_coordinates": {
        "latitude": 19.37753379846797,
        "elevation": 2481.502685546875,
        "longitude": -97.71052071042558
      },
      "timestamp": 1644447521908674955,
      "clipnumber": -1,
      "label": "LI_DAY",
      "clipname_video": "N/A",
      "state": "activated",
      "conditions": {
        "WeatherPrecipitation": [
          "PR_NO"
        ],
        "WeatherCloudiness": [
          "CL_PARTIALLY_CLOUDY"
        ],
        "WeatherLight": [
          "LI_DAY"
        ]
      },
      "type": "multi-select",
      "frame_number": 6352
    },
    {
      "category": "ConditionsRoadCategory",
      "postion_coordinates": {
        "latitude": 19.37772794376098,
        "elevation": 2483.663330078125,
        "longitude": -97.71008444791785
      },
      "timestamp": 1644447529032932996,
      "clipnumber": -1,
      "label": "RC_HIGHWAY",
      "clipname_video": "N/A",
      "state": "activated",
      "conditions": {
        "WeatherPrecipitation": [
          "PR_NO"
        ],
        "WeatherCloudiness": [
          "CL_PARTIALLY_CLOUDY"
        ],
        "ConditionsRoadCategory": [
          "RC_HIGHWAY"
        ],
        "WeatherLight": [
          "LI_DAY"
        ]
      },
      "type": "multi-select",
      "frame_number": 6608
    },
    {
      "category": "ConditionsRoadType",
      "postion_coordinates": {
        "latitude": 19.377871713917372,
        "elevation": 2485.16162109375,
        "longitude": -97.70982095693793
      },
      "timestamp": 1644447533368673086,
      "clipnumber": -1,
      "label": "RT_PAVED",
      "clipname_video": "N/A",
      "state": "activated",
      "conditions": {
        "WeatherPrecipitation": [
          "PR_NO"
        ],
        "ConditionsRoadType": [
          "RT_PAVED"
        ],
        "WeatherCloudiness": [
          "CL_PARTIALLY_CLOUDY"
        ],
        "ConditionsRoadCategory": [
          "RC_HIGHWAY"
        ],
        "WeatherLight": [
          "LI_DAY"
        ]
      },
      "type": "multi-select",
      "frame_number": 6784
    },
    {
      "category": "ConditionsRoadState",
      "postion_coordinates": {
        "latitude": 19.378062874013523,
        "elevation": 2486.942626953125,
        "longitude": -97.70953352510556
      },
      "timestamp": 1644447538438680887,
      "clipnumber": -1,
      "label": "ROAD_DRY",
      "clipname_video": "N/A",
      "state": "activated",
      "conditions": {
        "WeatherPrecipitation": [
          "PR_NO"
        ],
        "ConditionsRoadCategory": [
          "RC_HIGHWAY"
        ],
        "WeatherCloudiness": [
          "CL_PARTIALLY_CLOUDY"
        ],
        "ConditionsRoadState": [
          "ROAD_DRY"
        ],
        "ConditionsRoadType": [
          "RT_PAVED"
        ],
        "WeatherLight": [
          "LI_DAY"
        ]
      },
      "type": "multi-select",
      "frame_number": 6962
    },
    {
      "category": "OddObject",
      "postion_coordinates": {
        "latitude": 19.378661974118227,
        "elevation": 2491.156982421875,
        "longitude": -97.70886409195745
      },
      "timestamp": 1644447550478676080,
      "clipnumber": -1,
      "label": "OO_GENERAL_OBJ_VEHICLES",
      "clipname_video": "N/A",
      "state": "",
      "conditions": {
        "WeatherPrecipitation": [
          "PR_NO"
        ],
        "ConditionsRoadCategory": [
          "RC_HIGHWAY"
        ],
        "WeatherCloudiness": [
          "CL_PARTIALLY_CLOUDY"
        ],
        "ConditionsRoadState": [
          "ROAD_DRY"
        ],
        "ConditionsRoadType": [
          "RT_PAVED"
        ],
        "WeatherLight": [
          "LI_DAY"
        ]
      },
      "type": "single",
      "frame_number": 7396
    },
    {
      "category": "Signs",
      "postion_coordinates": {
        "latitude": 19.378754254996306,
        "elevation": 2491.86328125,
        "longitude": -97.708782208332
      },
      "timestamp": 1644447551468725919,
      "clipnumber": -1,
      "label": "SIGN_WARNING",
      "clipname_video": "N/A",
      "state": "",
      "conditions": {
        "WeatherPrecipitation": [
          "PR_NO"
        ],
        "ConditionsRoadCategory": [
          "RC_HIGHWAY"
        ],
        "WeatherCloudiness": [
          "CL_PARTIALLY_CLOUDY"
        ],
        "ConditionsRoadState": [
          "ROAD_DRY"
        ],
        "ConditionsRoadType": [
          "RT_PAVED"
        ],
        "WeatherLight": [
          "LI_DAY"
        ]
      },
      "type": "single",
      "frame_number": 7436
    },
    {
      "category": "Signs",
      "postion_coordinates": {
        "latitude": 19.378929521348926,
        "elevation": 2493.012451171875,
        "longitude": -97.70863900512326
      },
      "timestamp": 1644447553342686891,
      "clipnumber": -1,
      "label": "SIGN_SPEED_LIMIT_IMPLICIT",
      "clipname_video": "N/A",
      "state": "",
      "conditions": {
        "WeatherPrecipitation": [
          "PR_NO"
        ],
        "ConditionsRoadCategory": [
          "RC_HIGHWAY"
        ],
        "WeatherCloudiness": [
          "CL_PARTIALLY_CLOUDY"
        ],
        "ConditionsRoadState": [
          "ROAD_DRY"
        ],
        "ConditionsRoadType": [
          "RT_PAVED"
        ],
        "WeatherLight": [
          "LI_DAY"
        ]
      },
      "type": "single",
      "frame_number": 7508
    },
    {
      "category": "Signs",
      "postion_coordinates": {
        "latitude": 19.379175836137133,
        "elevation": 2494.66650390625,
        "longitude": -97.70845769491828
      },
      "timestamp": 1644447555568670988,
      "clipnumber": -1,
      "label": "SIGN_NO_PASSING",
      "clipname_video": "N/A",
      "state": "",
      "conditions": {
        "WeatherPrecipitation": [
          "PR_NO"
        ],
        "ConditionsRoadCategory": [
          "RC_HIGHWAY"
        ],
        "WeatherCloudiness": [
          "CL_PARTIALLY_CLOUDY"
        ],
        "ConditionsRoadState": [
          "ROAD_DRY"
        ],
        "ConditionsRoadType": [
          "RT_PAVED"
        ],
        "WeatherLight": [
          "LI_DAY"
        ]
      },
      "type": "single",
      "frame_number": 7584
    },
    {
      "category": "ConditionsLaneColor",
      "postion_coordinates": {
        "latitude": 19.37974694358169,
        "elevation": 2498.074462890625,
        "longitude": -97.7080970441527
      },
      "timestamp": 1644447560122549057,
      "clipnumber": -1,
      "label": "LC_YELLOW_BLUE",
      "clipname_video": "N/A",
      "state": "activated",
      "conditions": {
        "WeatherPrecipitation": [
          "PR_NO"
        ],
        "ConditionsLaneColor": [
          "LC_YELLOW_BLUE"
        ],
        "ConditionsRoadCategory": [
          "RC_HIGHWAY"
        ],
        "WeatherCloudiness": [
          "CL_PARTIALLY_CLOUDY"
        ],
        "ConditionsRoadState": [
          "ROAD_DRY"
        ],
        "ConditionsRoadType": [
          "RT_PAVED"
        ],
        "WeatherLight": [
          "LI_DAY"
        ]
      },
      "type": "multi-select",
      "frame_number": 7726
    },
    {
      "category": "ConditionsRoadEdge",
      "postion_coordinates": {
        "latitude": 19.380918574789042,
        "elevation": 2504.624267578125,
        "longitude": -97.7073672620468
      },
      "timestamp": 1644447568388710021,
      "clipnumber": -1,
      "label": "RE_CURB",
      "clipname_video": "N/A",
      "state": "",
      "conditions": {
        "WeatherPrecipitation": [
          "PR_NO"
        ],
        "ConditionsLaneColor": [
          "LC_YELLOW_BLUE"
        ],
        "ConditionsRoadCategory": [
          "RC_HIGHWAY"
        ],
        "WeatherCloudiness": [
          "CL_PARTIALLY_CLOUDY"
        ],
        "ConditionsRoadState": [
          "ROAD_DRY"
        ],
        "ConditionsRoadType": [
          "RT_PAVED"
        ],
        "WeatherLight": [
          "LI_DAY"
        ]
      },
      "type": "single",
      "frame_number": 8050
    },
    {
      "category": "Signs",
      "postion_coordinates": {
        "latitude": 19.381383403888048,
        "elevation": 2507.399169921875,
        "longitude": -97.70709200317106
      },
      "timestamp": 1644447571658652067,
      "clipnumber": -1,
      "label": "SIGN_SPEED_LIMIT_IMPLICIT",
      "clipname_video": "N/A",
      "state": "",
      "conditions": {
        "WeatherPrecipitation": [
          "PR_NO"
        ],
        "ConditionsLaneColor": [
          "LC_YELLOW_BLUE"
        ],
        "ConditionsRoadCategory": [
          "RC_HIGHWAY"
        ],
        "WeatherCloudiness": [
          "CL_PARTIALLY_CLOUDY"
        ],
        "ConditionsRoadState": [
          "ROAD_DRY"
        ],
        "ConditionsRoadType": [
          "RT_PAVED"
        ],
        "WeatherLight": [
          "LI_DAY"
        ]
      },
      "type": "single",
      "frame_number": 8158
    },
    {
      "category": "Signs",
      "postion_coordinates": {
        "latitude": 19.382002315590942,
        "elevation": 2510.974365234375,
        "longitude": -97.70672445725012
      },
      "timestamp": 1644447576418653011,
      "clipnumber": -1,
      "label": "SIGN_NO_PASSING",
      "clipname_video": "N/A",
      "state": "",
      "conditions": {
        "WeatherPrecipitation": [
          "PR_NO"
        ],
        "ConditionsLaneColor": [
          "LC_YELLOW_BLUE"
        ],
        "ConditionsRoadCategory": [
          "RC_HIGHWAY"
        ],
        "WeatherCloudiness": [
          "CL_PARTIALLY_CLOUDY"
        ],
        "ConditionsRoadState": [
          "ROAD_DRY"
        ],
        "ConditionsRoadType": [
          "RT_PAVED"
        ],
        "WeatherLight": [
          "LI_DAY"
        ]
      },
      "type": "single",
      "frame_number": 8340
    },
    {
      "category": "Signs",
      "postion_coordinates": {
        "latitude": 19.382545351360406,
        "elevation": 2514.25439453125,
        "longitude": -97.70640413326865
      },
      "timestamp": 1644447580648657083,
      "clipnumber": -1,
      "label": "SIGN_SPECIAL_TSR",
      "clipname_video": "N/A",
      "state": "",
      "conditions": {
        "WeatherPrecipitation": [
          "PR_NO"
        ],
        "ConditionsLaneColor": [
          "LC_YELLOW_BLUE"
        ],
        "ConditionsRoadCategory": [
          "RC_HIGHWAY"
        ],
        "WeatherCloudiness": [
          "CL_PARTIALLY_CLOUDY"
        ],
        "ConditionsRoadState": [
          "ROAD_DRY"
        ],
        "ConditionsRoadType": [
          "RT_PAVED"
        ],
        "WeatherLight": [
          "LI_DAY"
        ]
      },
      "type": "single",
      "frame_number": 8482
    },
    {
      "category": "Signs",
      "postion_coordinates": {
        "latitude": 19.383367591238247,
        "elevation": 2518.615966796875,
        "longitude": -97.705899495119
      },
      "timestamp": 1644447586249550104,
      "clipnumber": -1,
      "label": "SIGN_WARNING",
      "clipname_video": "N/A",
      "state": "",
      "conditions": {
        "WeatherPrecipitation": [
          "PR_NO"
        ],
        "ConditionsLaneColor": [
          "LC_YELLOW_BLUE"
        ],
        "ConditionsRoadCategory": [
          "RC_HIGHWAY"
        ],
        "WeatherCloudiness": [
          "CL_PARTIALLY_CLOUDY"
        ],
        "ConditionsRoadState": [
          "ROAD_DRY"
        ],
        "ConditionsRoadType": [
          "RT_PAVED"
        ],
        "WeatherLight": [
          "LI_DAY"
        ]
      },
      "type": "single",
      "frame_number": 8666
    },
    {
      "category": "Signs",
      "postion_coordinates": {
        "latitude": 19.384310886347315,
        "elevation": 2524.679443359375,
        "longitude": -97.7052019100807
      },
      "timestamp": 1644447592994395017,
      "clipnumber": -1,
      "label": "SIGN_EMBEDDED",
      "clipname_video": "N/A",
      "state": "",
      "conditions": {
        "WeatherPrecipitation": [
          "PR_NO"
        ],
        "ConditionsLaneColor": [
          "LC_YELLOW_BLUE"
        ],
        "ConditionsRoadCategory": [
          "RC_HIGHWAY"
        ],
        "WeatherCloudiness": [
          "CL_PARTIALLY_CLOUDY"
        ],
        "ConditionsRoadState": [
          "ROAD_DRY"
        ],
        "ConditionsRoadType": [
          "RT_PAVED"
        ],
        "WeatherLight": [
          "LI_DAY"
        ]
      },
      "type": "single",
      "frame_number": 8916
    },
    {
      "category": "Signs",
      "postion_coordinates": {
        "latitude": 19.384839966546124,
        "elevation": 2528.17236328125,
        "longitude": -97.70473365425431
      },
      "timestamp": 1644447596858700037,
      "clipnumber": -1,
      "label": "SIGN_NO_PASSING",
      "clipname_video": "N/A",
      "state": "",
      "conditions": {
        "WeatherPrecipitation": [
          "PR_NO"
        ],
        "ConditionsLaneColor": [
          "LC_YELLOW_BLUE"
        ],
        "ConditionsRoadCategory": [
          "RC_HIGHWAY"
        ],
        "WeatherCloudiness": [
          "CL_PARTIALLY_CLOUDY"
        ],
        "ConditionsRoadState": [
          "ROAD_DRY"
        ],
        "ConditionsRoadType": [
          "RT_PAVED"
        ],
        "WeatherLight": [
          "LI_DAY"
        ]
      },
      "type": "single",
      "frame_number": 9064
    },
    {
      "category": "ConditionsRoadEdge",
      "postion_coordinates": {
        "latitude": 19.385103033683173,
        "elevation": 2530.234130859375,
        "longitude": -97.7044714795795
      },
      "timestamp": 1644447599079334020,
      "clipnumber": -1,
      "label": "RE_GUARD_RAIL",
      "clipname_video": "N/A",
      "state": "",
      "conditions": {
        "WeatherPrecipitation": [
          "PR_NO"
        ],
        "ConditionsLaneColor": [
          "LC_YELLOW_BLUE"
        ],
        "ConditionsRoadCategory": [
          "RC_HIGHWAY"
        ],
        "WeatherCloudiness": [
          "CL_PARTIALLY_CLOUDY"
        ],
        "ConditionsRoadState": [
          "ROAD_DRY"
        ],
        "ConditionsRoadType": [
          "RT_PAVED"
        ],
        "WeatherLight": [
          "LI_DAY"
        ]
      },
      "type": "single",
      "frame_number": 9136
    },
    {
      "category": "Signs",
      "postion_coordinates": {
        "latitude": 19.385315739447762,
        "elevation": 2532.05126953125,
        "longitude": -97.70424522839623
      },
      "timestamp": 1644447601179657936,
      "clipnumber": -1,
      "label": "SIGN_SPEED_LIMIT_IMPLICIT",
      "clipname_video": "N/A",
      "state": "",
      "conditions": {
        "WeatherPrecipitation": [
          "PR_NO"
        ],
        "ConditionsLaneColor": [
          "LC_YELLOW_BLUE"
        ],
        "ConditionsRoadCategory": [
          "RC_HIGHWAY"
        ],
        "WeatherCloudiness": [
          "CL_PARTIALLY_CLOUDY"
        ],
        "ConditionsRoadState": [
          "ROAD_DRY"
        ],
        "ConditionsRoadType": [
          "RT_PAVED"
        ],
        "WeatherLight": [
          "LI_DAY"
        ]
      },
      "type": "single",
      "frame_number": 9206
    },
    {
      "category": "Signs",
      "postion_coordinates": {
        "latitude": 19.386048597980917,
        "elevation": 2538.899658203125,
        "longitude": -97.70336193885889
      },
      "timestamp": 1644447608358767986,
      "clipnumber": -1,
      "label": "SIGN_WARNING",
      "clipname_video": "N/A",
      "state": "",
      "conditions": {
        "WeatherPrecipitation": [
          "PR_NO"
        ],
        "ConditionsLaneColor": [
          "LC_YELLOW_BLUE"
        ],
        "ConditionsRoadCategory": [
          "RC_HIGHWAY"
        ],
        "WeatherCloudiness": [
          "CL_PARTIALLY_CLOUDY"
        ],
        "ConditionsRoadState": [
          "ROAD_DRY"
        ],
        "ConditionsRoadType": [
          "RT_PAVED"
        ],
        "WeatherLight": [
          "LI_DAY"
        ]
      },
      "type": "single",
      "frame_number": 9496
    },
    {
      "category": "Signs",
      "postion_coordinates": {
        "latitude": 19.38731532001542,
        "elevation": 2553.81591796875,
        "longitude": -97.70135947344866
      },
      "timestamp": 1644447623989223003,
      "clipnumber": -1,
      "label": "SIGN_SPEED_LIMIT_IMPLICIT",
      "clipname_video": "N/A",
      "state": "",
      "conditions": {
        "WeatherPrecipitation": [
          "PR_NO"
        ],
        "ConditionsLaneColor": [
          "LC_YELLOW_BLUE"
        ],
        "ConditionsRoadCategory": [
          "RC_HIGHWAY"
        ],
        "WeatherCloudiness": [
          "CL_PARTIALLY_CLOUDY"
        ],
        "ConditionsRoadState": [
          "ROAD_DRY"
        ],
        "ConditionsRoadType": [
          "RT_PAVED"
        ],
        "WeatherLight": [
          "LI_DAY"
        ]
      },
      "type": "single",
      "frame_number": 10034
    },
    {
      "category": "Signs",
      "postion_coordinates": {
        "latitude": 19.387428526242505,
        "elevation": 2555.24072265625,
        "longitude": -97.70117032839755
      },
      "timestamp": 1644447625458713054,
      "clipnumber": -1,
      "label": "SIGN_NO_PASSING",
      "clipname_video": "N/A",
      "state": "",
      "conditions": {
        "WeatherPrecipitation": [
          "PR_NO"
        ],
        "ConditionsLaneColor": [
          "LC_YELLOW_BLUE"
        ],
        "ConditionsRoadCategory": [
          "RC_HIGHWAY"
        ],
        "WeatherCloudiness": [
          "CL_PARTIALLY_CLOUDY"
        ],
        "ConditionsRoadState": [
          "ROAD_DRY"
        ],
        "ConditionsRoadType": [
          "RT_PAVED"
        ],
        "WeatherLight": [
          "LI_DAY"
        ]
      },
      "type": "single",
      "frame_number": 10106
    },
    {
      "category": "Signs",
      "postion_coordinates": {
        "latitude": 19.387827154796692,
        "elevation": 2559.9892578125,
        "longitude": -97.70050421943459
      },
      "timestamp": 1644447630718646049,
      "clipnumber": -1,
      "label": "SIGN_WARNING",
      "clipname_video": "N/A",
      "state": "",
      "conditions": {
        "WeatherPrecipitation": [
          "PR_NO"
        ],
        "ConditionsLaneColor": [
          "LC_YELLOW_BLUE"
        ],
        "ConditionsRoadCategory": [
          "RC_HIGHWAY"
        ],
        "WeatherCloudiness": [
          "CL_PARTIALLY_CLOUDY"
        ],
        "ConditionsRoadState": [
          "ROAD_DRY"
        ],
        "ConditionsRoadType": [
          "RT_PAVED"
        ],
        "WeatherLight": [
          "LI_DAY"
        ]
      },
      "type": "single",
      "frame_number": 10286
    },
    {
      "category": "Signs",
      "postion_coordinates": {
        "latitude": 19.38792898335712,
        "elevation": 2561.294189453125,
        "longitude": -97.70033209067111
      },
      "timestamp": 1644447631999063014,
      "clipnumber": -1,
      "label": "SIGN_NO_PASSING",
      "clipname_video": "N/A",
      "state": "",
      "conditions": {
        "WeatherPrecipitation": [
          "PR_NO"
        ],
        "ConditionsLaneColor": [
          "LC_YELLOW_BLUE"
        ],
        "ConditionsRoadCategory": [
          "RC_HIGHWAY"
        ],
        "WeatherCloudiness": [
          "CL_PARTIALLY_CLOUDY"
        ],
        "ConditionsRoadState": [
          "ROAD_DRY"
        ],
        "ConditionsRoadType": [
          "RT_PAVED"
        ],
        "WeatherLight": [
          "LI_DAY"
        ]
      },
      "type": "single",
      "frame_number": 10322
    },
    {
      "category": "Signs",
      "postion_coordinates": {
        "latitude": 19.388069388548214,
        "elevation": 2562.88427734375,
        "longitude": -97.700100254989
      },
      "timestamp": 1644447633728646993,
      "clipnumber": -1,
      "label": "SIGN_SPEED_LIMIT_IMPLICIT",
      "clipname_video": "N/A",
      "state": "",
      "conditions": {
        "WeatherPrecipitation": [
          "PR_NO"
        ],
        "ConditionsLaneColor": [
          "LC_YELLOW_BLUE"
        ],
        "ConditionsRoadCategory": [
          "RC_HIGHWAY"
        ],
        "WeatherCloudiness": [
          "CL_PARTIALLY_CLOUDY"
        ],
        "ConditionsRoadState": [
          "ROAD_DRY"
        ],
        "ConditionsRoadType": [
          "RT_PAVED"
        ],
        "WeatherLight": [
          "LI_DAY"
        ]
      },
      "type": "single",
      "frame_number": 10396
    },
    {
      "category": "Signs",
      "postion_coordinates": {
        "latitude": 19.388203846048636,
        "elevation": 2564.530029296875,
        "longitude": -97.69987627230934
      },
      "timestamp": 1644447635748761892,
      "clipnumber": -1,
      "label": "SIGN_WARNING",
      "clipname_video": "N/A",
      "state": "",
      "conditions": {
        "WeatherPrecipitation": [
          "PR_NO"
        ],
        "ConditionsLaneColor": [
          "LC_YELLOW_BLUE"
        ],
        "ConditionsRoadCategory": [
          "RC_HIGHWAY"
        ],
        "WeatherCloudiness": [
          "CL_PARTIALLY_CLOUDY"
        ],
        "ConditionsRoadState": [
          "ROAD_DRY"
        ],
        "ConditionsRoadType": [
          "RT_PAVED"
        ],
        "WeatherLight": [
          "LI_DAY"
        ]
      },
      "type": "single",
      "frame_number": 10468
    },
    {
      "category": "Signs",
      "postion_coordinates": {
        "latitude": 19.38830367635115,
        "elevation": 2565.779541015625,
        "longitude": -97.69970753824698
      },
      "timestamp": 1644447637078855991,
      "clipnumber": -1,
      "label": "SIGN_SPEED_LIMIT_EXPLICIT",
      "clipname_video": "N/A",
      "state": "",
      "conditions": {
        "WeatherPrecipitation": [
          "PR_NO"
        ],
        "ConditionsLaneColor": [
          "LC_YELLOW_BLUE"
        ],
        "ConditionsRoadCategory": [
          "RC_HIGHWAY"
        ],
        "WeatherCloudiness": [
          "CL_PARTIALLY_CLOUDY"
        ],
        "ConditionsRoadState": [
          "ROAD_DRY"
        ],
        "ConditionsRoadType": [
          "RT_PAVED"
        ],
        "WeatherLight": [
          "LI_DAY"
        ]
      },
      "type": "single",
      "frame_number": 10504
    },
    {
      "category": "Signs",
      "postion_coordinates": {
        "latitude": 19.38847447035486,
        "elevation": 2567.899658203125,
        "longitude": -97.69942516024363
      },
      "timestamp": 1644447639888672113,
      "clipnumber": -1,
      "label": "SIGN_PRIORITY",
      "clipname_video": "N/A",
      "state": "",
      "conditions": {
        "WeatherPrecipitation": [
          "PR_NO"
        ],
        "ConditionsLaneColor": [
          "LC_YELLOW_BLUE"
        ],
        "ConditionsRoadCategory": [
          "RC_HIGHWAY"
        ],
        "WeatherCloudiness": [
          "CL_PARTIALLY_CLOUDY"
        ],
        "ConditionsRoadState": [
          "ROAD_DRY"
        ],
        "ConditionsRoadType": [
          "RT_PAVED"
        ],
        "WeatherLight": [
          "LI_DAY"
        ]
      },
      "type": "single",
      "frame_number": 10608
    },
    {
      "category": "Signs",
      "postion_coordinates": {
        "latitude": 19.38866679368168,
        "elevation": 2570.421630859375,
        "longitude": -97.69910118224352
      },
      "timestamp": 1644447643029491901,
      "clipnumber": -1,
      "label": "SIGN_NO_PASSING",
      "clipname_video": "N/A",
      "state": "",
      "conditions": {
        "WeatherPrecipitation": [
          "PR_NO"
        ],
        "ConditionsLaneColor": [
          "LC_YELLOW_BLUE"
        ],
        "ConditionsRoadCategory": [
          "RC_HIGHWAY"
        ],
        "WeatherCloudiness": [
          "CL_PARTIALLY_CLOUDY"
        ],
        "ConditionsRoadState": [
          "ROAD_DRY"
        ],
        "ConditionsRoadType": [
          "RT_PAVED"
        ],
        "WeatherLight": [
          "LI_DAY"
        ]
      },
      "type": "single",
      "frame_number": 10718
    },
    {
      "category": "ConditionsRoadStructure",
      "postion_coordinates": {
        "latitude": 19.38882524174495,
        "elevation": 2572.3662109375,
        "longitude": -97.69883931254141
      },
      "timestamp": 1644447645818707942,
      "clipnumber": -1,
      "label": "RS_TUNNEL",
      "clipname_video": "N/A",
      "state": "activated",
      "conditions": {
        "WeatherPrecipitation": [
          "PR_NO"
        ],
        "ConditionsLaneColor": [
          "LC_YELLOW_BLUE"
        ],
        "ConditionsRoadCategory": [
          "RC_HIGHWAY"
        ],
        "ConditionsRoadStructure": [
          "RS_TUNNEL"
        ],
        "WeatherCloudiness": [
          "CL_PARTIALLY_CLOUDY"
        ],
        "ConditionsRoadState": [
          "ROAD_DRY"
        ],
        "ConditionsRoadType": [
          "RT_PAVED"
        ],
        "WeatherLight": [
          "LI_DAY"
        ]
      },
      "type": "multi-select",
      "frame_number": 10826
    },
    {
      "category": "ConditionsRoadEdge",
      "postion_coordinates": {
        "latitude": 19.388971733014245,
        "elevation": 2574.753662109375,
        "longitude": -97.69861398353419
      },
      "timestamp": 1644447648309320926,
      "clipnumber": -1,
      "label": "RE_CURB",
      "clipname_video": "N/A",
      "state": "",
      "conditions": {
        "WeatherPrecipitation": [
          "PR_NO"
        ],
        "ConditionsLaneColor": [
          "LC_YELLOW_BLUE"
        ],
        "ConditionsRoadCategory": [
          "RC_HIGHWAY"
        ],
        "ConditionsRoadStructure": [
          "RS_TUNNEL"
        ],
        "WeatherCloudiness": [
          "CL_PARTIALLY_CLOUDY"
        ],
        "ConditionsRoadState": [
          "ROAD_DRY"
        ],
        "ConditionsRoadType": [
          "RT_PAVED"
        ],
        "WeatherLight": [
          "LI_DAY"
        ]
      },
      "type": "single",
      "frame_number": 10897
    },
    {
      "category": "WeatherLight",
      "postion_coordinates": {
        "latitude": 19.38937966312683,
        "elevation": 2579.260009765625,
        "longitude": -97.69796043734831
      },
      "timestamp": 1644447655978841066,
      "clipnumber": -1,
      "label": "LI_DAY",
      "clipname_video": "N/A",
      "state": "deactivated",
      "conditions": {
        "WeatherPrecipitation": [
          "PR_NO"
        ],
        "ConditionsLaneColor": [
          "LC_YELLOW_BLUE"
        ],
        "ConditionsRoadCategory": [
          "RC_HIGHWAY"
        ],
        "ConditionsRoadStructure": [
          "RS_TUNNEL"
        ],
        "WeatherCloudiness": [
          "CL_PARTIALLY_CLOUDY"
        ],
        "ConditionsRoadState": [
          "ROAD_DRY"
        ],
        "ConditionsRoadType": [
          "RT_PAVED"
        ],
        "WeatherLight": []
      },
      "type": "multi-select",
      "frame_number": 11182
    },
    {
      "category": "WeatherLight",
      "postion_coordinates": {
        "latitude": 19.38937966312683,
        "elevation": 2579.260009765625,
        "longitude": -97.69796043734831
      },
      "timestamp": 1644447655978841066,
      "clipnumber": -1,
      "label": "LI_ARTIFICIAL",
      "clipname_video": "N/A",
      "state": "activated",
      "conditions": {
        "WeatherPrecipitation": [
          "PR_NO"
        ],
        "ConditionsLaneColor": [
          "LC_YELLOW_BLUE"
        ],
        "ConditionsRoadCategory": [
          "RC_HIGHWAY"
        ],
        "ConditionsRoadStructure": [
          "RS_TUNNEL"
        ],
        "WeatherCloudiness": [
          "CL_PARTIALLY_CLOUDY"
        ],
        "ConditionsRoadState": [
          "ROAD_DRY"
        ],
        "ConditionsRoadType": [
          "RT_PAVED"
        ],
        "WeatherLight": [
          "LI_ARTIFICIAL"
        ]
      },
      "type": "multi-select",
      "frame_number": 11182
    },
    {
      "category": "WeatherLight",
      "postion_coordinates": {
        "latitude": 19.389467493814102,
        "elevation": 2580.156005859375,
        "longitude": -97.6978132358407
      },
      "timestamp": 1644447657528799057,
      "clipnumber": -1,
      "label": "LI_ARTIFICIAL",
      "clipname_video": "N/A",
      "state": "deactivated",
      "conditions": {
        "WeatherPrecipitation": [
          "PR_NO"
        ],
        "ConditionsLaneColor": [
          "LC_YELLOW_BLUE"
        ],
        "ConditionsRoadCategory": [
          "RC_HIGHWAY"
        ],
        "ConditionsRoadStructure": [
          "RS_TUNNEL"
        ],
        "WeatherCloudiness": [
          "CL_PARTIALLY_CLOUDY"
        ],
        "ConditionsRoadState": [
          "ROAD_DRY"
        ],
        "ConditionsRoadType": [
          "RT_PAVED"
        ],
        "WeatherLight": []
      },
      "type": "multi-select",
      "frame_number": 11256
    },
    {
      "category": "WeatherLight",
      "postion_coordinates": {
        "latitude": 19.389467493814102,
        "elevation": 2580.156005859375,
        "longitude": -97.6978132358407
      },
      "timestamp": 1644447657528799057,
      "clipnumber": -1,
      "label": "LI_DAY",
      "clipname_video": "N/A",
      "state": "activated",
      "conditions": {
        "WeatherPrecipitation": [
          "PR_NO"
        ],
        "ConditionsLaneColor": [
          "LC_YELLOW_BLUE"
        ],
        "ConditionsRoadCategory": [
          "RC_HIGHWAY"
        ],
        "ConditionsRoadStructure": [
          "RS_TUNNEL"
        ],
        "WeatherCloudiness": [
          "CL_PARTIALLY_CLOUDY"
        ],
        "ConditionsRoadState": [
          "ROAD_DRY"
        ],
        "ConditionsRoadType": [
          "RT_PAVED"
        ],
        "WeatherLight": [
          "LI_DAY"
        ]
      },
      "type": "multi-select",
      "frame_number": 11256
    },
    {
      "category": "WeatherLight",
      "postion_coordinates": {
        "latitude": 19.38949998334239,
        "elevation": 2580.474365234375,
        "longitude": -97.69775827529618
      },
      "timestamp": 1644447658240134954,
      "clipnumber": -1,
      "label": "LI_DAY",
      "clipname_video": "N/A",
      "state": "deactivated",
      "conditions": {
        "WeatherPrecipitation": [
          "PR_NO"
        ],
        "ConditionsLaneColor": [
          "LC_YELLOW_BLUE"
        ],
        "ConditionsRoadCategory": [
          "RC_HIGHWAY"
        ],
        "ConditionsRoadStructure": [
          "RS_TUNNEL"
        ],
        "WeatherCloudiness": [
          "CL_PARTIALLY_CLOUDY"
        ],
        "ConditionsRoadState": [
          "ROAD_DRY"
        ],
        "ConditionsRoadType": [
          "RT_PAVED"
        ],
        "WeatherLight": []
      },
      "type": "multi-select",
      "frame_number": 11256
    },
    {
      "category": "WeatherLight",
      "postion_coordinates": {
        "latitude": 19.38949998334239,
        "elevation": 2580.474365234375,
        "longitude": -97.69775827529618
      },
      "timestamp": 1644447658240134954,
      "clipnumber": -1,
      "label": "LI_ARTIFICIAL",
      "clipname_video": "N/A",
      "state": "activated",
      "conditions": {
        "WeatherPrecipitation": [
          "PR_NO"
        ],
        "ConditionsLaneColor": [
          "LC_YELLOW_BLUE"
        ],
        "ConditionsRoadCategory": [
          "RC_HIGHWAY"
        ],
        "ConditionsRoadStructure": [
          "RS_TUNNEL"
        ],
        "WeatherCloudiness": [
          "CL_PARTIALLY_CLOUDY"
        ],
        "ConditionsRoadState": [
          "ROAD_DRY"
        ],
        "ConditionsRoadType": [
          "RT_PAVED"
        ],
        "WeatherLight": [
          "LI_ARTIFICIAL"
        ]
      },
      "type": "multi-select",
      "frame_number": 11256
    },
    {
      "category": "ConditionsLaneColor",
      "postion_coordinates": {
        "latitude": 19.390036721712743,
        "elevation": 2584.9208984375,
        "longitude": -97.6967780056317
      },
      "timestamp": 1644447668249212026,
      "clipnumber": -1,
      "label": "LC_YELLOW_BLUE",
      "clipname_video": "N/A",
      "state": "deactivated",
      "conditions": {
        "WeatherPrecipitation": [
          "PR_NO"
        ],
        "ConditionsLaneColor": [],
        "ConditionsRoadCategory": [
          "RC_HIGHWAY"
        ],
        "ConditionsRoadStructure": [
          "RS_TUNNEL"
        ],
        "WeatherCloudiness": [
          "CL_PARTIALLY_CLOUDY"
        ],
        "ConditionsRoadState": [
          "ROAD_DRY"
        ],
        "ConditionsRoadType": [
          "RT_PAVED"
        ],
        "WeatherLight": [
          "LI_ARTIFICIAL"
        ]
      },
      "type": "multi-select",
      "frame_number": 11615
    },
    {
      "category": "ConditionsRoadStructure",
      "postion_coordinates": {
        "latitude": 19.390870301100314,
        "elevation": 2587.9150390625,
        "longitude": -97.69433161160664
      },
      "timestamp": 1644447694758735895,
      "clipnumber": -1,
      "label": "RS_TUNNEL",
      "clipname_video": "N/A",
      "state": "deactivated",
      "conditions": {
        "WeatherPrecipitation": [
          "PR_NO"
        ],
        "ConditionsLaneColor": [],
        "ConditionsRoadCategory": [
          "RC_HIGHWAY"
        ],
        "ConditionsRoadStructure": [],
        "WeatherCloudiness": [
          "CL_PARTIALLY_CLOUDY"
        ],
        "ConditionsRoadState": [
          "ROAD_DRY"
        ],
        "ConditionsRoadType": [
          "RT_PAVED"
        ],
        "WeatherLight": [
          "LI_ARTIFICIAL"
        ]
      },
      "type": "multi-select",
      "frame_number": 12592
    },
    {
      "category": "WeatherLight",
      "postion_coordinates": {
        "latitude": 19.390930057235245,
        "elevation": 2587.793212890625,
        "longitude": -97.69401187981883
      },
      "timestamp": 1644447699181227922,
      "clipnumber": -1,
      "label": "LI_ARTIFICIAL",
      "clipname_video": "N/A",
      "state": "deactivated",
      "conditions": {
        "WeatherPrecipitation": [
          "PR_NO"
        ],
        "ConditionsLaneColor": [],
        "ConditionsRoadCategory": [
          "RC_HIGHWAY"
        ],
        "ConditionsRoadStructure": [],
        "WeatherCloudiness": [
          "CL_PARTIALLY_CLOUDY"
        ],
        "ConditionsRoadState": [
          "ROAD_DRY"
        ],
        "ConditionsRoadType": [
          "RT_PAVED"
        ],
        "WeatherLight": []
      },
      "type": "multi-select",
      "frame_number": 12728
    },
    {
      "category": "WeatherLight",
      "postion_coordinates": {
        "latitude": 19.390930057235245,
        "elevation": 2587.793212890625,
        "longitude": -97.69401187981883
      },
      "timestamp": 1644447699181227922,
      "clipnumber": -1,
      "label": "LI_DAY",
      "clipname_video": "N/A",
      "state": "activated",
      "conditions": {
        "WeatherPrecipitation": [
          "PR_NO"
        ],
        "ConditionsLaneColor": [],
        "ConditionsRoadCategory": [
          "RC_HIGHWAY"
        ],
        "ConditionsRoadStructure": [],
        "WeatherCloudiness": [
          "CL_PARTIALLY_CLOUDY"
        ],
        "ConditionsRoadState": [
          "ROAD_DRY"
        ],
        "ConditionsRoadType": [
          "RT_PAVED"
        ],
        "WeatherLight": [
          "LI_DAY"
        ]
      },
      "type": "multi-select",
      "frame_number": 12728
    },
    {
      "category": "Signs",
      "postion_coordinates": {
        "latitude": 19.390953163192624,
        "elevation": 2587.606689453125,
        "longitude": -97.69384960197836
      },
      "timestamp": 1644447701408967971,
      "clipnumber": -1,
      "label": "SIGN_NO_PASSING",
      "clipname_video": "N/A",
      "state": "",
      "conditions": {
        "WeatherPrecipitation": [
          "PR_NO"
        ],
        "ConditionsLaneColor": [],
        "ConditionsRoadCategory": [
          "RC_HIGHWAY"
        ],
        "ConditionsRoadStructure": [],
        "WeatherCloudiness": [
          "CL_PARTIALLY_CLOUDY"
        ],
        "ConditionsRoadState": [
          "ROAD_DRY"
        ],
        "ConditionsRoadType": [
          "RT_PAVED"
        ],
        "WeatherLight": [
          "LI_DAY"
        ]
      },
      "type": "single",
      "frame_number": 12834
    },
    {
      "category": "ConditionsRoadEdge",
      "postion_coordinates": {
        "latitude": 19.390984066532493,
        "elevation": 2587.616455078125,
        "longitude": -97.69359550829316
      },
      "timestamp": 1644447705618689060,
      "clipnumber": -1,
      "label": "RE_CURB",
      "clipname_video": "N/A",
      "state": "",
      "conditions": {
        "WeatherPrecipitation": [
          "PR_NO"
        ],
        "ConditionsLaneColor": [],
        "ConditionsRoadCategory": [
          "RC_HIGHWAY"
        ],
        "ConditionsRoadStructure": [],
        "WeatherCloudiness": [
          "CL_PARTIALLY_CLOUDY"
        ],
        "ConditionsRoadState": [
          "ROAD_DRY"
        ],
        "ConditionsRoadType": [
          "RT_PAVED"
        ],
        "WeatherLight": [
          "LI_DAY"
        ]
      },
      "type": "single",
      "frame_number": 12976
    },
    {
      "category": "WeatherPrecipitation",
      "postion_coordinates": {
        "latitude": 19.391263638969694,
        "elevation": 2568.9814453125,
        "longitude": -97.69134881537013
      },
      "timestamp": 1644447743889215946,
      "clipnumber": -1,
      "label": "PR_NO",
      "clipname_video": "N/A",
      "state": "deactivated",
      "conditions": {},
      "type": "multi-select",
      "frame_number": 14356
    },
    {
      "category": "ConditionsRoadCategory",
      "postion_coordinates": {
        "latitude": 19.391263638969694,
        "elevation": 2568.9814453125,
        "longitude": -97.69134881537013
      },
      "timestamp": 1644447743889215946,
      "clipnumber": -1,
      "label": "RC_HIGHWAY",
      "clipname_video": "N/A",
      "state": "deactivated",
      "conditions": {},
      "type": "multi-select",
      "frame_number": 14356
    },
    {
      "category": "WeatherCloudiness",
      "postion_coordinates": {
        "latitude": 19.391263638969694,
        "elevation": 2568.9814453125,
        "longitude": -97.69134881537013
      },
      "timestamp": 1644447743889215946,
      "clipnumber": -1,
      "label": "CL_PARTIALLY_CLOUDY",
      "clipname_video": "N/A",
      "state": "deactivated",
      "conditions": {},
      "type": "multi-select",
      "frame_number": 14356
    },
    {
      "category": "ConditionsRoadState",
      "postion_coordinates": {
        "latitude": 19.391263638969694,
        "elevation": 2568.9814453125,
        "longitude": -97.69134881537013
      },
      "timestamp": 1644447743889215946,
      "clipnumber": -1,
      "label": "ROAD_DRY",
      "clipname_video": "N/A",
      "state": "deactivated",
      "conditions": {},
      "type": "multi-select",
      "frame_number": 14356
    },
    {
      "category": "ConditionsRoadType",
      "postion_coordinates": {
        "latitude": 19.391263638969694,
        "elevation": 2568.9814453125,
        "longitude": -97.69134881537013
      },
      "timestamp": 1644447743889215946,
      "clipnumber": -1,
      "label": "RT_PAVED",
      "clipname_video": "N/A",
      "state": "deactivated",
      "conditions": {},
      "type": "multi-select",
      "frame_number": 14356
    },
    {
      "category": "WeatherLight",
      "postion_coordinates": {
        "latitude": 19.391263638969694,
        "elevation": 2568.9814453125,
        "longitude": -97.69134881537013
      },
      "timestamp": 1644447743889215946,
      "clipnumber": -1,
      "label": "LI_DAY",
      "clipname_video": "N/A",
      "state": "deactivated",
      "conditions": {},
      "type": "multi-select",
      "frame_number": 14356
    }
  ]
}